Workbook

Sheet 說明
A1: 1019課程版本：各出版商國高中課本目錄統整
A3: 資料範圍
A4: 國中：翰林、康軒、南一，7–9 年級上下冊。國文、英文、數學、自然（生物、理化、地球科學）、社會（歷史、地理、公民）。
A5: 高中：三民、龍騰、南一、全華、泰宇。10 科部定必修與加深加廣選修。
A6: 以 115 學年度現行版本為準；只找到 114 學年度資料時，「學年度」欄會註明。
A8: 資料來源與限制
A9: 蒐集時，出版商官網在作業環境中無法連線（網路政策阻擋），因此本版資料來自網路搜尋，主要是各校公開的課程計畫與教學計畫表，每列都附來源網址。
A10: 只收錄來源中實際看到、且明確標示版本的章節；查不到的冊次保留一列，章節空白（黃底），不做推測。
A11: 學校課程計畫的單元名稱可能經過學校簡化或調整，與課本原文可能有些微差異；以出版商官網或課本為準。
A12: 待辦：開放出版商網域後，到官網逐冊核對，並補上空白冊次；核對過的列，「來源類型」會改為「出版商官網」。
A13: 官網網域：翰林 hle.com.tw、康軒 knsh.com.tw、南一 nani.com.tw、三民 sanmin.com.tw、龍騰 ltedu.com.tw、全華 chwa.com.tw、泰宇 tyedu.com.tw（泰宇待確認）。
A15: 欄位說明
... A19: 目前共 1293 列，其中 988 列有章節內容。

Sheet 國中
A1: 版本 | B1: 學段 | C1: 年級 | D1: 冊次 | E1: 科目 | F1: 章 | G1: 節 | H1: 學年度 | I1: 來源類型 | J1: 來源網址 | K1: 備註
A2: 翰林 | B2: 國中 | C2: 7 | D2: 上 | E2: 國文 | F2: 第一課 夏夜 | H2: 115 | I2: 出版商頁面 | J2: https://sites.google.com/hanlin.com.tw/112chwebppt/1%E4%B8%8A | K2: 來源為翰林官方Google Sites「國文網頁版PPT」課次清單，頁面標示【115上】入口；經搜尋摘要擷取，非直接開啟頁面
A3: 翰林 | B3: 國中 | C3: 7 | D3: 上 | E3: 國文 | F3: 第二課 無心的錯誤 | H3: 115 | I3: 出版商頁面 | J3: https://sites.google.com/hanlin.com.tw/112chwebppt/1%E4%B8%8A | K3: 來源為翰林官方Google Sites「國文網頁版PPT」課次清單，頁面標示【115上】入口；經搜尋摘要擷取，非直接開啟頁面
A4: 翰林 | B4: 國中 | C4: 7 | D4: 上 | E4: 國文 | F4: 第三課 母親的教誨 | H4: 115 | I4: 出版商頁面 | J4: https://sites.google.com/hanlin.com.tw/112chwebppt/1%E4%B8%8A | K4: 來源為翰林官方Google Sites「國文網頁版PPT」課次清單，頁面標示【115上】入口；經搜尋摘要擷取，非直接開啟頁面
A5: 翰林 | B5: 國中 | C5: 7 | D5: 上 | E5: 國文 | F5: 語文常識一 標點符號使用法 | H5: 115 | I5: 出版商頁面 | J5: https://sites.google.com/hanlin.com.tw/112chwebppt/1%E4%B8%8A | K5: 來源為翰林官方Google Sites「國文網頁版PPT」課次清單，頁面標示【115上】入口；經搜尋摘要擷取，非直接開啟頁面
A6: 翰林 | B6: 國中 | C6: 7 | D6: 上 | E6: 國文 | F6: 第四課 論語選 | H6: 115 | I6: 出版商頁面 | J6: https://sites.google.com/hanlin.com.tw/112chwebppt/1%E4%B8%8A | K6: 來源為翰林官方Google Sites「國文網頁版PPT」課次清單，頁面標示【115上】入口；經搜尋摘要擷取，非直接開啟頁面
A7: 翰林 | B7: 國中 | C7: 7 | D7: 上 | E7: 國文 | F7: 第五課 背影 | H7: 115 | I7: 出版商頁面 | J7: https://sites.google.com/hanlin.com.tw/112chwebppt/1%E4%B8%8A | K7: 來源為翰林官方Google Sites「國文網頁版PPT」課次清單，頁面標示【115上】入口；經搜尋摘要擷取，非直接開啟頁面
A8: 翰林 | B8: 國中 | C8: 7 | D8: 上 | E8: 國文 | F8: 第六課 心囚 | H8: 115 | I8: 出版商頁面 | J8: https://sites.google.com/hanlin.com.tw/112chwebppt/1%E4%B8%8A | K8: 來源為翰林官方Google Sites「國文網頁版PPT」課次清單，頁面標示【115上】入口；經搜尋摘要擷取，非直接開啟頁面
A9: 翰林 | B9: 國中 | C9: 7 | D9: 上 | E9: 國文 | F9: 語文常識二 策略運用與資訊檢索 | H9: 115 | I9: 出版商頁面 | J9: https://sites.google.com/hanlin.com.tw/112chwebppt/1%E4%B8%8A | K9: 來源為翰林官方Google Sites「國文網頁版PPT」課次清單，頁面標示【115上】入口；經搜尋摘要擷取，非直接開啟頁面
A10: 翰林 | B10: 國中 | C10: 7 | D10: 上 | E10: 國文 | F10: 第七課 兒時記趣 | H10: 115 | I10: 出版商頁面 | J10: https://sites.google.com/hanlin.com.tw/112chwebppt/1%E4%B8%8A | K10: 來源為翰林官方Google Sites「國文網頁版PPT」課次清單，頁面標示【115上】入口；經搜尋摘要擷取，非直接開啟頁面
A11: 翰林 | B11: 國中 | C11: 7 | D11: 上 | E11: 國文 | F11: 第八課 朋友相交 | H11: 115 | I11: 出版商頁面 | J11: https://sites.google.com/hanlin.com.tw/112chwebppt/1%E4%B8%8A | K11: 來源為翰林官方Google Sites「國文網頁版PPT」課次清單，頁面標示【115上】入口；經搜尋摘要擷取，非直接開啟頁面
A12: 翰林 | B12: 國中 | C12: 7 | D12: 上 | E12: 國文 | F12: 第九課 音樂家與職籃巨星 | H12: 115 | I12: 出版商頁面 | J12: https://sites.google.com/hanlin.com.tw/112chwebppt/1%E4%B8%8A | K12: 來源為翰林官方Google Sites「國文網頁版PPT」課次清單，頁面標示【115上】入口；經搜尋摘要擷取，非直接開啟頁面
A13: 翰林 | B13: 國中 | C13: 7 | D13: 上 | E13: 國文 | F13: 第十課 玫瑰淚 | H13: 115 | I13: 出版商頁面 | J13: https://sites.google.com/hanlin.com.tw/112chwebppt/1%E4%B8%8A | K13: 來源為翰林官方Google Sites「國文網頁版PPT」課次清單，頁面標示【115上】入口；經搜尋摘要擷取，非直接開啟頁面；翰林114學年度「數位互動資源平台」將L10列為〈藍色串珠項鍊〉，與此處不同
... A115: 翰林 | B115: 國中 | C115: 9 | D115: 下 | E115: 英文 | F115: Unit 4 Let’s Vote | H115: 115 | I115: 出版商官網 | J115: https://dl.hle.com.tw/1151/國中/01課程計畫/115翰林課程計畫_英語教學進度總表.zip | K115: 來源為翰林官網行動大師「115課程計畫-教學進度總表」壓縮檔內《115三下英語(二次段考)課程總表.doc》;Review單元及延伸活動未列入,節未列;主題:台灣的公民參與
A116: 翰林 | B116: 國中 | C116: 7 | D116: 上 | E116: 數學 | F116: 第1章 數與數線 | G116: 1-1 正數與負數；1-2 正負數的加減；1-3 正負數的乘除；1-4 指數記法與科學記號 | H116: 115 | I116: 出版商官網 | J116: https://dl.hle.com.tw/1151/國中/01課程計畫/115翰林課程計畫_數學教學進度總表.zip | K116: 來源為翰林官網行動大師「115課程計畫-教學進度總表」壓縮檔內《115一上數學(三次段考)課程總表.doc》;節名取自進度表;進度表僅列「節」編號,未含實驗等細項
A117: 翰林 | B117: 國中 | C117: 7 | D117: 上 | E117: 數學 | F117: 第2章 標準分解式與分數運算 | G117: 2-1 質因數分解；2-2 最大公因數與最小公倍數；2-3 分數的四則運算；2-4 指數律 | H117: 115 | I117: 出版商官網 | J117: https://dl.hle.com.tw/1151/國中/01課程計畫/115翰林課程計畫_數學教學進度總表.zip | K117: 來源為翰林官網行動大師「115課程計畫-教學進度總表」壓縮檔內《115一上數學(三次段考)課程總表.doc》;節名取自進度表;進度表僅列「節」編號,未含實驗等細項
A118: 翰林 | B118: 國中 | C118: 7 | D118: 上 | E118: 數學 | F118: 第3章 一元一次方程式 | G118: 3-1 式子的運算；3-2 解一元一次方程式；3-3 應用問題 | H118: 115 | I118: 出版商官網 | J118: https://dl.hle.com.tw/1151/國中/01課程計畫/115翰林課程計畫_數學教學進度總表.zip | K118: 來源為翰林官網行動大師「115課程計畫-教學進度總表」壓縮檔內《115一上數學(三次段考)課程總表.doc》;節名取自進度表;進度表僅列「節」編號,未含實驗等細項
A119: 翰林 | B119: 國中 | C119: 7 | D119: 下 | E119: 數學 | F119: 第1章 二元一次聯立方程式 | G119: 1-1 二元一次方程式；1-2 解二元一次聯立方程式；1-3 應用問題 | H119: 115 | I119: 出版商官網 | J119: https://dl.hle.com.tw/1151/國中/01課程計畫/115翰林課程計畫_數學教學進度總表.zip | K119: 來源為翰林官網行動大師「115課程計畫-教學進度總表」壓縮檔內《115一下數學(三次段考)課程總表.doc》;節名取自進度表;進度表僅列「節」編號,未含實驗等細項
A120: 翰林 | B120: 國中 | C120: 7 | D120: 下 | E120: 數學 | F120: 第2章 直角坐標與二元一次方程式的圖形 | G120: 2-1 直角坐標平面；2-2 二元一次方程式的圖形 | H120: 115 | I120: 出版商官網 | J120: https://dl.hle.com.tw/1151/國中/01課程計畫/115翰林課程計畫_數學教學進度總表.zip | K120: 來源為翰林官網行動大師「115課程計畫-教學進度總表」壓縮檔內《115一下數學(三次段考)課程總表.doc》;節名取自進度表;進度表僅列「節」編號,未含實驗等細項
A121: 翰林 | B121: 國中 | C121: 7 | D121: 下 | E121: 數學 | F121: 第3章 比例 | G121: 3-1 比例式；3-2 正比與反比 | H121: 115 | I121: 出版商官網 | J121: https://dl.hle.com.tw/1151/國中/01課程計畫/115翰林課程計畫_數學教學進度總表.zip | K121: 來源為翰林官網行動大師「115課程計畫-教學進度總表」壓縮檔內《115一下數學(三次段考)課程總表.doc》;節名取自進度表;進度表僅列「節」編號,未含實驗等細項
A122: 翰林 | B122: 國中 | C122: 7 | D122: 下 | E122: 數學 | F122: 第4章 一元一次不等式 | G122: 4-1 一元一次不等式的解及圖示；4-2 解一元一次不等式及其應用 | H122: 115 | I122: 出版商官網 | J122: https://dl.hle.com.tw/1151/國中/01課程計畫/115翰林課程計畫_數學教學進度總表.zip | K122: 來源為翰林官網行動大師「115課程計畫-教學進度總表」壓縮檔內《115一下數學(三次段考)課程總表.doc》;節名取自進度表;進度表僅列「節」編號,未含實驗等細項
A123: 翰林 | B123: 國中 | C123: 7 | D123: 下 | E123: 數學 | F123: 第5章 統計圖表與統計數據 | H123: 115 | I123: 出版商官網 | J123: https://dl.hle.com.tw/1151/國中/01課程計畫/115翰林課程計畫_數學教學進度總表.zip | K123: 來源為翰林官網行動大師「115課程計畫-教學進度總表」壓縮檔內《115一下數學(三次段考)課程總表.doc》;節名取自進度表;進度表僅列「節」編號,未含實驗等細項
A124: 翰林 | B124: 國中 | C124: 7 | D124: 下 | E124: 數學 | F124: 第6章 線對稱與三視圖 | H124: 115 | I124: 出版商官網 | J124: https://dl.hle.com.tw/1151/國中/01課程計畫/115翰林課程計畫_數學教學進度總表.zip | K124: 來源為翰林官網行動大師「115課程計畫-教學進度總表」壓縮檔內《115一下數學(三次段考)課程總表.doc》;節名取自進度表;進度表僅列「節」編號,未含實驗等細項
A125: 翰林 | B125: 國中 | C125: 8 | D125: 上 | E125: 數學 | F125: 第1章 乘法公式與多項式 | G125: 1-1 乘法公式；1-2 多項式的加減；1-3 多項式的乘除 | H125: 115 | I125: 出版商官網 | J125: https://dl.hle.com.tw/1151/國中/01課程計畫/115翰林課程計畫_數學教學進度總表.zip | K125: 來源為翰林官網行動大師「115課程計畫-教學進度總表」壓縮檔內《115二上數學(三次段考)課程總表.doc》;節名取自進度表;進度表僅列「節」編號,未含實驗等細項
A126: 翰林 | B126: 國中 | C126: 8 | D126: 上 | E126: 數學 | F126: 第2章 二次方根與畢氏定理 | G126: 2-1 二次方根的意義；2-2 根式的運算；2-3 畢氏定理 | H126: 115 | I126: 出版商官網 | J126: https://dl.hle.com.tw/1151/國中/01課程計畫/115翰林課程計畫_數學教學進度總表.zip | K126: 來源為翰林官網行動大師「115課程計畫-教學進度總表」壓縮檔內《115二上數學(三次段考)課程總表.doc》;節名取自進度表;進度表僅列「節」編號,未含實驗等細項
A127: 翰林 | B127: 國中 | C127: 8 | D127: 上 | E127: 數學 | F127: 第3章 因式分解 | G127: 3-1 提公因式與乘法公式作因式分解；3-2 利用十字交乘法因式分解 | H127: 115 | I127: 出版商官網 | J127: https://dl.hle.com.tw/1151/國中/01課程計畫/115翰林課程計畫_數學教學進度總表.zip | K127: 來源為翰林官網行動大師「115課程計畫-教學進度總表」壓縮檔內《115二上數學(三次段考)課程總表.doc》;節名取自進度表;進度表僅列「節」編號,未含實驗等細項
A128: 翰林 | B128: 國中 | C128: 8 | D128: 上 | E128: 數學 | F128: 第4章 一元二次方程式 | G128: 4-1 因式分解法解一元二次方程式；4-2 配方法與公式解；4-3 應用問題 | H128: 115 | I128: 出版商官網 | J128: https://dl.hle.com.tw/1151/國中/01課程計畫/115翰林課程計畫_數學教學進度總表.zip | K128: 來源為翰林官網行動大師「115課程計畫-教學進度總表」壓縮檔內《115二上數學(三次段考)課程總表.doc》;節名取自進度表;進度表僅列「節」編號,未含實驗等細項
A129: 翰林 | B129: 國中 | C129: 8 | D129: 上 | E129: 數學 | F129: 第5章 統計資料處理 | H129: 115 | I129: 出版商官網 | J129: https://dl.hle.com.tw/1151/國中/01課程計畫/115翰林課程計畫_數學教學進度總表.zip | K129: 來源為翰林官網行動大師「115課程計畫-教學進度總表」壓縮檔內《115二上數學(三次段考)課程總表.doc》;節名取自進度表;進度表僅列「節」編號,未含實驗等細項
A130: 翰林 | B130: 國中 | C130: 8 | D130: 下 | E130: 數學 | F130: 第1章 數列與級數 | G130: 1-1 認識數列與等差數列；1-2 等差級數；1-3 等比數列 | H130: 115 | I130: 出版商官網 | J130: https://dl.hle.com.tw/1151/國中/01課程計畫/115翰林課程計畫_數學教學進度總表.zip | K130: 來源為翰林官網行動大師「115課程計畫-教學進度總表」壓縮檔內《115二下數學(三次段考)課程總表.doc》;節名取自進度表;進度表僅列「節」編號,未含實驗等細項
A131: 翰林 | B131: 國中 | C131: 8 | D131: 下 | E131: 數學 | F131: 第2章 線型函數與其圖形 | H131: 115 | I131: 出版商官網 | J131: https://dl.hle.com.tw/1151/國中/01課程計畫/115翰林課程計畫_數學教學進度總表.zip | K131: 來源為翰林官網行動大師「115課程計畫-教學進度總表」壓縮檔內《115二下數學(三次段考)課程總表.doc》;節名取自進度表;進度表僅列「節」編號,未含實驗等細項
A132: 翰林 | B132: 國中 | C132: 8 | D132: 下 | E132: 數學 | F132: 第3章 三角形的基本性質 | G132: 3-1 內角與外角；3-2 基本的尺規作圖；3-3 三角形的全等性質；3-4 中垂線與角平分線性質；3-5 三角形的邊角關係 | H132: 115 | I132: 出版商官網 | J132: https://dl.hle.com.tw/1151/國中/01課程計畫/115翰林課程計畫_數學教學進度總表.zip | K132: 來源為翰林官網行動大師「115課程計畫-教學進度總表」壓縮檔內《115二下數學(三次段考)課程總表.doc》;節名取自進度表;進度表僅列「節」編號,未含實驗等細項
A133: 翰林 | B133: 國中 | C133: 8 | D133: 下 | E133: 數學 | F133: 第4章 平行與四邊形 | G133: 4-1 平行線與截角性質；4-2 平行四邊形；4-3 特殊四邊形 | H133: 115 | I133: 出版商官網 | J133: https://dl.hle.com.tw/1151/國中/01課程計畫/115翰林課程計畫_數學教學進度總表.zip | K133: 來源為翰林官網行動大師「115課程計畫-教學進度總表」壓縮檔內《115二下數學(三次段考)課程總表.doc》;節名取自進度表;進度表僅列「節」編號,未含實驗等細項
A134: 翰林 | B134: 國中 | C134: 9 | D134: 上 | E134: 數學 | F134: 第1章 相似形與三角比 | G134: 1-1 連比；1-2 比例線段；1-3 相似多邊形；1-4 相似三角形的應用與三角比 | H134: 115 | I134: 出版商官網 | J134: https://dl.hle.com.tw/1151/國中/01課程計畫/115翰林課程計畫_數學教學進度總表.zip | K134: 來源為翰林官網行動大師「115課程計畫-教學進度總表」壓縮檔內《115三上數學(三次段考)課程總表.doc》;節名取自進度表;進度表僅列「節」編號,未含實驗等細項
A135: 翰林 | B135: 國中 | C135: 9 | D135: 上 | E135: 數學 | F135: 第2章 圓形 | G135: 2-1 點、線、圓；2-2 圓心角與圓周角 | H135: 115 | I135: 出版商官網 | J135: https://dl.hle.com.tw/1151/國中/01課程計畫/115翰林課程計畫_數學教學進度總表.zip | K135: 來源為翰林官網行動大師「115課程計畫-教學進度總表」壓縮檔內《115三上數學(三次段考)課程總表.doc》;節名取自進度表;進度表僅列「節」編號,未含實驗等細項
A136: 翰林 | B136: 國中 | C136: 9 | D136: 上 | E136: 數學 | F136: 第3章 推理證明與三角形的心 | G136: 3-1 推理證明；3-2 三角形的外心、內心與重心 | H136: 115 | I136: 出版商官網 | J136: https://dl.hle.com.tw/1151/國中/01課程計畫/115翰林課程計畫_數學教學進度總表.zip | K136: 來源為翰林官網行動大師「115課程計畫-教學進度總表」壓縮檔內《115三上數學(三次段考)課程總表.doc》;節名取自進度表;進度表僅列「節」編號,未含實驗等細項
A137: 翰林 | B137: 國中 | C137: 9 | D137: 下 | E137: 數學 | F137: 第1章 二次函數 | G137: 1-1 基本二次函數的圖形；1-2 二次函數圖形與最大值、最小值 | H137: 115 | I137: 出版商官網 | J137: https://dl.hle.com.tw/1151/國中/01課程計畫/115翰林課程計畫_數學教學進度總表.zip | K137: 來源為翰林官網行動大師「115課程計畫-教學進度總表」壓縮檔內《115三下數學(二次段考)課程總表.doc》;節名取自進度表;進度表僅列「節」編號,未含實驗等細項
A138: 翰林 | B138: 國中 | C138: 9 | D138: 下 | E138: 數學 | F138: 第2章 統計與機率 | G138: 2-1 四分位數與盒狀圖；2-2 機率 | H138: 115 | I138: 出版商官網 | J138: https://dl.hle.com.tw/1151/國中/01課程計畫/115翰林課程計畫_數學教學進度總表.zip | K138: 來源為翰林官網行動大師「115課程計畫-教學進度總表」壓縮檔內《115三下數學(二次段考)課程總表.doc》;節名取自進度表;進度表僅列「節」編號,未含實驗等細項
A139: 翰林 | B139: 國中 | C139: 9 | D139: 下 | E139: 數學 | F139: 第3章 立體圖形 | H139: 115 | I139: 出版商官網 | J139: https://dl.hle.com.tw/1151/國中/01課程計畫/115翰林課程計畫_數學教學進度總表.zip | K139: 來源為翰林官網行動大師「115課程計畫-教學進度總表」壓縮檔內《115三下數學(二次段考)課程總表.doc》;節名取自進度表;進度表僅列「節」編號,未含實驗等細項
A140: 翰林 | B140: 國中 | C140: 7 | D140: 上 | E140: 生物 | F140: 第1章 生命世界與科學方法 | G140: 1-1 多采多姿的生命世界；1-2 探究自然的科學方法；1-3 進入實驗室 | H140: 115 | I140: 出版商官網 | J140: https://dl.hle.com.tw/1151/國中/01課程計畫/115翰林課程計畫_自然教學進度總表.zip | K140: 來源為翰林官網行動大師「115課程計畫-教學進度總表」壓縮檔內《115一上自然(三次段考)課程總表.doc》;節名取自進度表,實驗/探討活動未列入
A141: 翰林 | B141: 國中 | C141: 7 | D141: 上 | E141: 生物 | F141: 第2章 生物體的組成 | G141: 2-1 生物的基本單位；2-2 細胞的構造；2-3 物質進出細胞的方式；2-4 生物體的組成層次 | H141: 115 | I141: 出版商官網 | J141: https://dl.hle.com.tw/1151/國中/01課程計畫/115翰林課程計畫_自然教學進度總表.zip | K141: 來源為翰林官網行動大師「115課程計畫-教學進度總表」壓縮檔內《115一上自然(三次段考)課程總表.doc》;節名取自進度表,實驗/探討活動未列入
A142: 翰林 | B142: 國中 | C142: 7 | D142: 上 | E142: 生物 | F142: 第3章 生物體的營養 | G142: 3-1 食物中的養分與能量；3-2 酵素；3-3 植物如何製造養分；3-4 人體如何獲得養分 | H142: 115 | I142: 出版商官網 | J142: https://dl.hle.com.tw/1151/國中/01課程計畫/115翰林課程計畫_自然教學進度總表.zip | K142: 來源為翰林官網行動大師「115課程計畫-教學進度總表」壓縮檔內《115一上自然(三次段考)課程總表.doc》;節名取自進度表,實驗/探討活動未列入
A143: 翰林 | B143: 國中 | C143: 7 | D143: 上 | E143: 生物 | F143: 第4章 生物體的運輸作用 | G143: 4-1 植物的運輸構造；4-2 植物體內物質的運輸；4-3 人體血液循環的組成；4-4 人體的循環系統 | H143: 115 | I143: 出版商官網 | J143: https://dl.hle.com.tw/1151/國中/01課程計畫/115翰林課程計畫_自然教學進度總表.zip | K143: 來源為翰林官網行動大師「115課程計畫-教學進度總表」壓縮檔內《115一上自然(三次段考)課程總表.doc》;節名取自進度表,實驗/探討活動未列入
A144: 翰林 | B144: 國中 | C144: 7 | D144: 上 | E144: 生物 | F144: 第5章 生物體的協調作用 | G144: 5-1 刺激與反應；5-2 神經系統；5-3 內分泌系統；5-4 行為與感應 | H144: 115 | I144: 出版商官網 | J144: https://dl.hle.com.tw/1151/國中/01課程計畫/115翰林課程計畫_自然教學進度總表.zip | K144: 來源為翰林官網行動大師「115課程計畫-教學進度總表」壓縮檔內《115一上自然(三次段考)課程總表.doc》;節名取自進度表,實驗/探討活動未列入
A145: 翰林 | B145: 國中 | C145: 7 | D145: 上 | E145: 生物 | F145: 第6章 生物體的恆定 | G145: 6-1 呼吸與氣體的恆定；6-2 排泄與水分的恆定；6-3 體溫的恆定與血糖的恆定 | H145: 115 | I145: 出版商官網 | J145: https://dl.hle.com.tw/1151/國中/01課程計畫/115翰林課程計畫_自然教學進度總表.zip | K145: 來源為翰林官網行動大師「115課程計畫-教學進度總表」壓縮檔內《115一上自然(三次段考)課程總表.doc》;節名取自進度表,實驗/探討活動未列入
A146: 翰林 | B146: 國中 | C146: 7 | D146: 上 | E146: 生物 | F146: 跨科主題-尺度 | G146: 微觀與巨觀；尺度與單位；比例尺；微觀世界的觀察 | H146: 115 | I146: 出版商官網 | J146: https://dl.hle.com.tw/1151/國中/01課程計畫/115翰林課程計畫_自然教學進度總表.zip | K146: 來源為翰林官網行動大師「115課程計畫-教學進度總表」壓縮檔內《115一上自然(三次段考)課程總表.doc》;節名取自進度表,實驗/探討活動未列入;進度表列為跨科主題,細項層級待核對
A147: 翰林 | B147: 國中 | C147: 7 | D147: 下 | E147: 生物 | F147: 第1章 生殖 | G147: 1-1 細胞的分裂；1-2 無性生殖；1-3 有性生殖 | H147: 115 | I147: 出版商官網 | J147: https://dl.hle.com.tw/1151/國中/01課程計畫/115翰林課程計畫_自然教學進度總表.zip | K147: 來源為翰林官網行動大師「115課程計畫-教學進度總表」壓縮檔內《115一下自然(三次段考)課程總表.doc》;節名取自進度表,實驗/探討活動未列入
A148: 翰林 | B148: 國中 | C148: 7 | D148: 下 | E148: 生物 | F148: 第2章 遺傳 | G148: 2-1 遺傳、染色體與基因；2-2 人類的遺傳；2-3 突變與遺傳諮詢；2-4 生物技術 | H148: 115 | I148: 出版商官網 | J148: https://dl.hle.com.tw/1151/國中/01課程計畫/115翰林課程計畫_自然教學進度總表.zip | K148: 來源為翰林官網行動大師「115課程計畫-教學進度總表」壓縮檔內《115一下自然(三次段考)課程總表.doc》;節名取自進度表,實驗/探討活動未列入
A149: 翰林 | B149: 國中 | C149: 7 | D149: 下 | E149: 生物 | F149: 第3章 生物的演化與分類 | G149: 3-1 化石與演化；3-2 生物的命名與分類；3-3 原核、原生生物界及真菌界；3-4 植物界；3-5 動物界 | H149: 115 | I149: 出版商官網 | J149: https://dl.hle.com.tw/1151/國中/01課程計畫/115翰林課程計畫_自然教學進度總表.zip | K149: 來源為翰林官網行動大師「115課程計畫-教學進度總表」壓縮檔內《115一下自然(三次段考)課程總表.doc》;節名取自進度表,實驗/探討活動未列入
A150: 翰林 | B150: 國中 | C150: 7 | D150: 下 | E150: 生物 | F150: 第4章 生物與環境 | G150: 4-1 族群、群集與演替；4-2 生物間的互動關係；4-3 生態系；4-4 生態系的類型 | H150: 115 | I150: 出版商官網 | J150: https://dl.hle.com.tw/1151/國中/01課程計畫/115翰林課程計畫_自然教學進度總表.zip | K150: 來源為翰林官網行動大師「115課程計畫-教學進度總表」壓縮檔內《115一下自然(三次段考)課程總表.doc》;節名取自進度表,實驗/探討活動未列入
A151: 翰林 | B151: 國中 | C151: 7 | D151: 下 | E151: 生物 | F151: 第5章 環境保護與生態平衡 | G151: 5-1 生物多樣性；5-2 生物多樣性面臨的危機；5-3 保育的落實 | H151: 115 | I151: 出版商官網 | J151: https://dl.hle.com.tw/1151/國中/01課程計畫/115翰林課程計畫_自然教學進度總表.zip | K151: 來源為翰林官網行動大師「115課程計畫-教學進度總表」壓縮檔內《115一下自然(三次段考)課程總表.doc》;節名取自進度表,實驗/探討活動未列入
A152: 翰林 | B152: 國中 | C152: 7 | D152: 下 | E152: 生物 | F152: 跨科主題 環境的永續發展 | H152: 115 | I152: 出版商官網 | J152: https://dl.hle.com.tw/1151/國中/01課程計畫/115翰林課程計畫_自然教學進度總表.zip | K152: 來源為翰林官網行動大師「115課程計畫-教學進度總表」壓縮檔內《115一下自然(三次段考)課程總表.doc》;節名取自進度表,實驗/探討活動未列入;進度表列為跨科主題
A153: 翰林 | B153: 國中 | C153: 8 | D153: 上 | E153: 理化 | F153: 第一章 基本測量 | G153: 1-1 長度、質量與時間；1-2 測量與估計；1-3 體積與密度的測量 | H153: 115 | I153: 出版商官網 | J153: https://dl.hle.com.tw/1151/國中/01課程計畫/115翰林課程計畫_自然教學進度總表.zip | K153: 來源為翰林官網行動大師「115課程計畫-教學進度總表」壓縮檔內《115二上自然(三次段考)課程總表.doc》;節名取自進度表,實驗/探討活動未列入
A154: 翰林 | B154: 國中 | C154: 8 | D154: 上 | E154: 理化 | F154: 第二章 物質的世界 | G154: 2-1 認識物質；2-2 溶液與濃度；2-3 混合物的分離 | H154: 115 | I154: 出版商官網 | J154: https://dl.hle.com.tw/1151/國中/01課程計畫/115翰林課程計畫_自然教學進度總表.zip | K154: 來源為翰林官網行動大師「115課程計畫-教學進度總表」壓縮檔內《115二上自然(三次段考)課程總表.doc》;節名取自進度表,實驗/探討活動未列入
A155: 翰林 | B155: 國中 | C155: 8 | D155: 上 | E155: 理化 | F155: 第三章 波動與聲音 | G155: 3-1 波的傳播與特徵；3-2 聲音的形成；3-3 多變的聲音；3-4 聲波的傳播與應用 | H155: 115 | I155: 出版商官網 | J155: https://dl.hle.com.tw/1151/國中/01課程計畫/115翰林課程計畫_自然教學進度總表.zip | K155: 來源為翰林官網行動大師「115課程計畫-教學進度總表」壓縮檔內《115二上自然(三次段考)課程總表.doc》;節名取自進度表,實驗/探討活動未列入
A156: 翰林 | B156: 國中 | C156: 8 | D156: 上 | E156: 理化 | F156: 第四章 光、影像與顏色 | G156: 4-1 光的傳播；4-2 光的反射與面鏡成像；4-3 光的折射；4-4 透鏡成像；4-5 色散與顏色 | H156: 115 | I156: 出版商官網 | J156: https://dl.hle.com.tw/1151/國中/01課程計畫/115翰林課程計畫_自然教學進度總表.zip | K156: 來源為翰林官網行動大師「115課程計畫-教學進度總表」壓縮檔內《115二上自然(三次段考)課程總表.doc》;節名取自進度表,實驗/探討活動未列入
A157: 翰林 | B157: 國中 | C157: 8 | D157: 上 | E157: 理化 | F157: 第五章 溫度與熱 | G157: 5-1 溫度與溫度計；5-2 熱量；5-3 比熱；5-4 熱對物質的影響；5-5 熱的傳播方式 | H157: 115 | I157: 出版商官網 | J157: https://dl.hle.com.tw/1151/國中/01課程計畫/115翰林課程計畫_自然教學進度總表.zip | K157: 來源為翰林官網行動大師「115課程計畫-教學進度總表」壓縮檔內《115二上自然(三次段考)課程總表.doc》;節名取自進度表,實驗/探討活動未列入
A158: 翰林 | B158: 國中 | C158: 8 | D158: 上 | E158: 理化 | F158: 第六章 物質的基本結構 | G158: 6-1 元素與化合物；6-2 生活中常見的元素；6-3 物質結構與原子；6-4 週期表；6-5 分子與化學式 | H158: 115 | I158: 出版商官網 | J158: https://dl.hle.com.tw/1151/國中/01課程計畫/115翰林課程計畫_自然教學進度總表.zip | K158: 來源為翰林官網行動大師「115課程計畫-教學進度總表」壓縮檔內《115二上自然(三次段考)課程總表.doc》;節名取自進度表,實驗/探討活動未列入
A159: 翰林 | B159: 國中 | C159: 8 | D159: 上 | E159: 理化 | F159: 跨科主題 | G159: 生命的原動力；地球的能源；太陽的畫布；紅外線的發現；光的直進性與日地月運動；光傳播速率的測量 | H159: 115 | I159: 出版商官網 | J159: https://dl.hle.com.tw/1151/國中/01課程計畫/115翰林課程計畫_自然教學進度總表.zip | K159: 來源為翰林官網行動大師「115課程計畫-教學進度總表」壓縮檔內《115二上自然(三次段考)課程總表.doc》;節名取自進度表,實驗/探討活動未列入;進度表列為跨科主題
A160: 翰林 | B160: 國中 | C160: 8 | D160: 下 | E160: 理化 | F160: 第一章 化學反應 | G160: 1-1 質量守恆定律；1-2 反應式與化學計量 | H160: 115 | I160: 出版商官網 | J160: https://dl.hle.com.tw/1151/國中/01課程計畫/115翰林課程計畫_自然教學進度總表.zip | K160: 來源為翰林官網行動大師「115課程計畫-教學進度總表」壓縮檔內《115二下自然(三次段考)課程總表.doc》;節名取自進度表,實驗/探討活動未列入
A161: 翰林 | B161: 國中 | C161: 8 | D161: 下 | E161: 理化 | F161: 第二章 氧化還原反應 | G161: 2-1 氧化反應與活性；2-2 氧化與還原反應 | H161: 115 | I161: 出版商官網 | J161: https://dl.hle.com.tw/1151/國中/01課程計畫/115翰林課程計畫_自然教學進度總表.zip | K161: 來源為翰林官網行動大師「115課程計畫-教學進度總表」壓縮檔內《115二下自然(三次段考)課程總表.doc》;節名取自進度表,實驗/探討活動未列入
A162: 翰林 | B162: 國中 | C162: 8 | D162: 下 | E162: 理化 | F162: 第三章 電解質與酸鹼鹽 | G162: 3-1 電解質；3-2 酸和鹼；3-3 酸鹼的強弱與pH值；3-4 酸鹼反應 | H162: 115 | I162: 出版商官網 | J162: https://dl.hle.com.tw/1151/國中/01課程計畫/115翰林課程計畫_自然教學進度總表.zip | K162: 來源為翰林官網行動大師「115課程計畫-教學進度總表」壓縮檔內《115二下自然(三次段考)課程總表.doc》;節名取自進度表,實驗/探討活動未列入
A163: 翰林 | B163: 國中 | C163: 8 | D163: 下 | E163: 理化 | F163: 第四章 反應速率與平衡 | G163: 4-1 反應速率；4-2 可逆反應與平衡 | H163: 115 | I163: 出版商官網 | J163: https://dl.hle.com.tw/1151/國中/01課程計畫/115翰林課程計畫_自然教學進度總表.zip | K163: 來源為翰林官網行動大師「115課程計畫-教學進度總表」壓縮檔內《115二下自然(三次段考)課程總表.doc》;節名取自進度表,實驗/探討活動未列入
A164: 翰林 | B164: 國中 | C164: 8 | D164: 下 | E164: 理化 | F164: 第五章 有機化合物 | G164: 5-1 有機化合物的組成；5-2 常見的有機化合物；5-3 聚合物與衣料纖維；5-4 食品與清潔劑 | H164: 115 | I164: 出版商官網 | J164: https://dl.hle.com.tw/1151/國中/01課程計畫/115翰林課程計畫_自然教學進度總表.zip | K164: 來源為翰林官網行動大師「115課程計畫-教學進度總表」壓縮檔內《115二下自然(三次段考)課程總表.doc》;節名取自進度表,實驗/探討活動未列入
... A178: 翰林 | B178: 國中 | C178: 9 | D178: 下 | E178: 地球科學 | F178: 第4章 永續的地球 | G178: 4-1 海洋與大氣的互動；4-2 全球變遷；4-3 人與自然的互動 | H178: 115 | I178: 出版商官網 | J178: https://dl.hle.com.tw/1151/國中/01課程計畫/115翰林課程計畫_自然教學進度總表.zip | K178: 來源為翰林官網行動大師「115課程計畫-教學進度總表」壓縮檔內《115三下自然(分科)(二次段考)課程總表.doc》;節名取自進度表,實驗/探討活動未列入
A179: 翰林 | B179: 國中 | C179: 9 | D179: 下 | E179: 地球科學 | F179: 跨科主題 氣候變遷與調適 | H179: 115 | I179: 出版商官網 | J179: https://dl.hle.com.tw/1151/國中/01課程計畫/115翰林課程計畫_自然教學進度總表.zip | K179: 來源為翰林官網行動大師「115課程計畫-教學進度總表」壓縮檔內《115三下自然(分科)(二次段考)課程總表.doc》;節名取自進度表,實驗/探討活動未列入;進度表列為跨科主題
A180: 翰林 | B180: 國中 | C180: 7 | D180: 上 | E180: 社會-公民 | F180: 第三篇 公民身分及社群 第一章 公民與公民德性 | H180: 115 | I180: 出版商官網 | J180: https://dl.hle.com.tw/1151/國中/01課程計畫/115翰林課程計畫_社會教學進度總表.zip | K180: 來源為翰林官網行動大師「115課程計畫-教學進度總表」壓縮檔內《115一上社會(分科)(三次段考)課程總表.doc》;進度表只列篇/章;節名未查到(電子書需登入;官網教材樣書為2022年舊版,未採用)
A181: 翰林 | B181: 國中 | C181: 7 | D181: 上 | E181: 社會-公民 | F181: 第三篇 公民身分及社群 第二章 人性尊嚴與人權保障 | H181: 115 | I181: 出版商官網 | J181: https://dl.hle.com.tw/1151/國中/01課程計畫/115翰林課程計畫_社會教學進度總表.zip | K181: 來源為翰林官網行動大師「115課程計畫-教學進度總表」壓縮檔內《115一上社會(分科)(三次段考)課程總表.doc》;進度表只列篇/章;節名未查到(電子書需登入;官網教材樣書為2022年舊版,未採用)
A182: 翰林 | B182: 國中 | C182: 7 | D182: 上 | E182: 社會-公民 | F182: 第三篇 公民身分及社群 第三章 家庭生活 | H182: 115 | I182: 出版商官網 | J182: https://dl.hle.com.tw/1151/國中/01課程計畫/115翰林課程計畫_社會教學進度總表.zip | K182: 來源為翰林官網行動大師「115課程計畫-教學進度總表」壓縮檔內《115一上社會(分科)(三次段考)課程總表.doc》;進度表只列篇/章;節名未查到(電子書需登入;官網教材樣書為2022年舊版,未採用)
A183: 翰林 | B183: 國中 | C183: 7 | D183: 上 | E183: 社會-公民 | F183: 第三篇 公民身分及社群 第四章 變遷中的家庭 | H183: 115 | I183: 出版商官網 | J183: https://dl.hle.com.tw/1151/國中/01課程計畫/115翰林課程計畫_社會教學進度總表.zip | K183: 來源為翰林官網行動大師「115課程計畫-教學進度總表」壓縮檔內《115一上社會(分科)(三次段考)課程總表.doc》;進度表只列篇/章;節名未查到(電子書需登入;官網教材樣書為2022年舊版,未採用)
A184: 翰林 | B184: 國中 | C184: 7 | D184: 上 | E184: 社會-公民 | F184: 第三篇 公民身分及社群 第五章 學生權利與校園生活 | H184: 115 | I184: 出版商官網 | J184: https://dl.hle.com.tw/1151/國中/01課程計畫/115翰林課程計畫_社會教學進度總表.zip | K184: 來源為翰林官網行動大師「115課程計畫-教學進度總表」壓縮檔內《115一上社會(分科)(三次段考)課程總表.doc》;進度表只列篇/章;節名未查到(電子書需登入;官網教材樣書為2022年舊版,未採用)
A185: 翰林 | B185: 國中 | C185: 7 | D185: 上 | E185: 社會-公民 | F185: 第三篇 公民身分及社群 第六章 部落與公民參與 | H185: 115 | I185: 出版商官網 | J185: https://dl.hle.com.tw/1151/國中/01課程計畫/115翰林課程計畫_社會教學進度總表.zip | K185: 來源為翰林官網行動大師「115課程計畫-教學進度總表」壓縮檔內《115一上社會(分科)(三次段考)課程總表.doc》;進度表只列篇/章;節名未查到(電子書需登入;官網教材樣書為2022年舊版,未採用)
A186: 翰林 | B186: 國中 | C186: 7 | D186: 下 | E186: 社會-公民 | F186: 第三篇 公民與社會生活 第一章 多元文化 | H186: 115 | I186: 出版商官網 | J186: https://dl.hle.com.tw/1151/國中/01課程計畫/115翰林課程計畫_社會教學進度總表.zip | K186: 來源為翰林官網行動大師「115課程計畫-教學進度總表」壓縮檔內《115一下社會(分科)(三次段考)課程總表.doc》;進度表只列篇/章;節名未查到(電子書需登入;官網教材樣書為2022年舊版,未採用)
A187: 翰林 | B187: 國中 | C187: 7 | D187: 下 | E187: 社會-公民 | F187: 第三篇 公民與社會生活 第二章 社會規範 | H187: 115 | I187: 出版商官網 | J187: https://dl.hle.com.tw/1151/國中/01課程計畫/115翰林課程計畫_社會教學進度總表.zip | K187: 來源為翰林官網行動大師「115課程計畫-教學進度總表」壓縮檔內《115一下社會(分科)(三次段考)課程總表.doc》;進度表只列篇/章;節名未查到(電子書需登入;官網教材樣書為2022年舊版,未採用)
A188: 翰林 | B188: 國中 | C188: 7 | D188: 下 | E188: 社會-公民 | F188: 第三篇 公民與社會生活 第三章 團體與志願結社 | H188: 115 | I188: 出版商官網 | J188: https://dl.hle.com.tw/1151/國中/01課程計畫/115翰林課程計畫_社會教學進度總表.zip | K188: 來源為翰林官網行動大師「115課程計畫-教學進度總表」壓縮檔內《115一下社會(分科)(三次段考)課程總表.doc》;進度表只列篇/章;節名未查到(電子書需登入;官網教材樣書為2022年舊版,未採用)
A189: 翰林 | B189: 國中 | C189: 7 | D189: 下 | E189: 社會-公民 | F189: 第三篇 公民與社會生活 第四章 公共意見 | H189: 115 | I189: 出版商官網 | J189: https://dl.hle.com.tw/1151/國中/01課程計畫/115翰林課程計畫_社會教學進度總表.zip | K189: 來源為翰林官網行動大師「115課程計畫-教學進度總表」壓縮檔內《115一下社會(分科)(三次段考)課程總表.doc》;進度表只列篇/章;節名未查到(電子書需登入;官網教材樣書為2022年舊版,未採用)
A190: 翰林 | B190: 國中 | C190: 7 | D190: 下 | E190: 社會-公民 | F190: 第三篇 公民與社會生活 第五章 公平正義 | H190: 115 | I190: 出版商官網 | J190: https://dl.hle.com.tw/1151/國中/01課程計畫/115翰林課程計畫_社會教學進度總表.zip | K190: 來源為翰林官網行動大師「115課程計畫-教學進度總表」壓縮檔內《115一下社會(分科)(三次段考)課程總表.doc》;進度表只列篇/章;節名未查到(電子書需登入;官網教材樣書為2022年舊版,未採用)
... A403: 康軒 | B403: 國中 | C403: 9 | D403: 下 | E403: 英文 | F403: 議題融入教學Ⅴ-挺身反霸凌 | H403: 115 | I403: 出版商官網 | J403: https://drive.google.com/file/d/174J5chtTX5nEIClhPzaya9qDZprb9eFM/view | K403: 康軒官網 www.knsh.com.tw/service/plan「國中課程(康軒版)」連結之雲端資料夾檔案「橫式115(二)中英3下三次考查課程計畫.docx」(115學年度課程計畫範本,週次表);章節取自「單元主題」「課程名稱」欄,已略去複習/評量週。
A404: 康軒 | B404: 國中 | C404: 7 | D404: 上 | E404: 數學 | F404: 第1章 整數的運算 | G404: 1-1 負數與數線；1-2 整數的加減；1-3 整數的乘除與四則運算；1-4 指數記法與科學記號 | H404: 112 | I404: 其他 | J404: https://www.learnmode.net/course/592128/content | K404: 節名取自 LearnMode「(112學年) 康軒版─國中數學【七上】」目錄；彰化縣大村國中115學年度課程計畫（康軒版）可見第1章整數的運算、1-1 負數與數線、1-3 整數的乘除與四則運算，與此一致：https://www.curriculum.chc.edu.tw/storage/137/115/5-7%E6%95%B8%E5%AD%B8.pdf/PHHKAaoTMrf14KSv1nEscC86VW94PnKbCuS3kRSx.pdf
A405: 康軒 | B405: 國中 | C405: 7 | D405: 上 | E405: 數學 | F405: 第2章 分數的運算 | G405: 2-1 因數與倍數；2-2 最大公因數與最小公倍數；2-3 分數的四則運算；2-4 指數律 | H405: 112 | I405: 其他 | J405: https://www.learnmode.net/course/592128/content | K405: 取自 LearnMode 112學年康軒版七上目錄；未找到115學年度明確節名
A406: 康軒 | B406: 國中 | C406: 7 | D406: 上 | E406: 數學 | F406: 第3章 一元一次方程式 | G406: 3-1 代數式的化簡；3-2 一元一次方程式；3-3 應用問題 | H406: 112 | I406: 其他 | J406: https://www.learnmode.net/course/592128/content | K406: 取自 LearnMode 112學年康軒版七上目錄；均一「類康軒版」節名不同（3-1 以符號列式與運算等），以 LearnMode 為準
A407: 康軒 | B407: 國中 | C407: 7 | D407: 下 | E407: 數學 | F407: 第5章 統計 | G407: 5-1 統計圖表與資料分析 | H407: 115 | I407: 出版商官網 | J407: https://drive.google.com/file/d/1VjtF1LJxdCw7yiqFGQrUTpLJYhfuX6Mv/view | K407: 康軒官網 www.knsh.com.tw/service/plan「國中課程(康軒版)」連結之雲端資料夾檔案「橫式115(二)中數1下三次考查課程計畫.docx」(115學年度課程計畫範本,週次表);章節取自「單元主題」「課程名稱」欄,已略去複習/評量週。
A408: 康軒 | B408: 國中 | C408: 7 | D408: 下 | E408: 數學 | F408: 第6章 生活中的幾何 | G408: 6-1 垂直、線對稱與三視圖 | H408: 115 | I408: 出版商官網 | J408: https://drive.google.com/file/d/1VjtF1LJxdCw7yiqFGQrUTpLJYhfuX6Mv/view | K408: 康軒官網 www.knsh.com.tw/service/plan「國中課程(康軒版)」連結之雲端資料夾檔案「橫式115(二)中數1下三次考查課程計畫.docx」(115學年度課程計畫範本,週次表);章節取自「單元主題」「課程名稱」欄,已略去複習/評量週。
A409: 康軒 | B409: 國中 | C409: 8 | D409: 上 | E409: 數學 | F409: 一、乘法公式與多項式 | G409: 1-1 乘法公式；1-2 多項式與其加減運算；1-3 多項式的乘除運算 | H409: 115 | I409: 出版商官網 | J409: https://drive.google.com/file/d/1SdQgGd0xNRWbN3_J-5i5eTd-n9UmbjYO/view | K409: 康軒官網 www.knsh.com.tw/service/plan「國中課程(康軒版)」連結之雲端資料夾檔案「橫式115(一)中數2上三次考查課程計畫.docx」(115學年度課程計畫範本,週次表);章節取自「單元主題」「課程名稱」欄,已略去複習/評量週。
A410: 康軒 | B410: 國中 | C410: 8 | D410: 上 | E410: 數學 | F410: 二、平方根與畢氏定理 | G410: 2-1 平方根與近似值；2-2 根式的運算；2-3 畢氏定理 | H410: 115 | I410: 出版商官網 | J410: https://drive.google.com/file/d/1SdQgGd0xNRWbN3_J-5i5eTd-n9UmbjYO/view | K410: 康軒官網 www.knsh.com.tw/service/plan「國中課程(康軒版)」連結之雲端資料夾檔案「橫式115(一)中數2上三次考查課程計畫.docx」(115學年度課程計畫範本,週次表);章節取自「單元主題」「課程名稱」欄,已略去複習/評量週。
A411: 康軒 | B411: 國中 | C411: 8 | D411: 上 | E411: 數學 | F411: 三、因式分解 | G411: 3-1 利用提公因式或乘法公式做因式分解；3-2 利用十字交乘法做因式分解 | H411: 115 | I411: 出版商官網 | J411: https://drive.google.com/file/d/1SdQgGd0xNRWbN3_J-5i5eTd-n9UmbjYO/view | K411: 康軒官網 www.knsh.com.tw/service/plan「國中課程(康軒版)」連結之雲端資料夾檔案「橫式115(一)中數2上三次考查課程計畫.docx」(115學年度課程計畫範本,週次表);章節取自「單元主題」「課程名稱」欄,已略去複習/評量週。
A412: 康軒 | B412: 國中 | C412: 8 | D412: 上 | E412: 數學 | F412: 四、一元二次方程式 | G412: 4-1 因式分解解一元二次方程式；4-2 配方法與公式解；4-3 應用問題 | H412: 115 | I412: 出版商官網 | J412: https://drive.google.com/file/d/1SdQgGd0xNRWbN3_J-5i5eTd-n9UmbjYO/view | K412: 康軒官網 www.knsh.com.tw/service/plan「國中課程(康軒版)」連結之雲端資料夾檔案「橫式115(一)中數2上三次考查課程計畫.docx」(115學年度課程計畫範本,週次表);章節取自「單元主題」「課程名稱」欄,已略去複習/評量週。
A413: 康軒 | B413: 國中 | C413: 8 | D413: 上 | E413: 數學 | F413: 五、統計資料處理 | G413: 5-1 資料整理與統計圖表 | H413: 115 | I413: 出版商官網 | J413: https://drive.google.com/file/d/1SdQgGd0xNRWbN3_J-5i5eTd-n9UmbjYO/view | K413: 康軒官網 www.knsh.com.tw/service/plan「國中課程(康軒版)」連結之雲端資料夾檔案「橫式115(一)中數2上三次考查課程計畫.docx」(115學年度課程計畫範本,週次表);章節取自「單元主題」「課程名稱」欄,已略去複習/評量週。
A414: 康軒 | B414: 國中 | C414: 8 | D414: 下 | E414: 數學 | F414: 第1章 數列與級數 | G414: 1-1 等差數列；1-2 等差級數；1-3 等比數列 | H414: 112 | I414: 其他 | J414: https://www.learnmode.net/course/638732/content | K414: 取自 LearnMode「(112學年) 康軒版─國中數學【八下】」目錄；未找到115學年度明確節名
A415: 康軒 | B415: 國中 | C415: 8 | D415: 下 | E415: 數學 | F415: 第2章 函數 | G415: 2-1 函數與函數圖形 | H415: 112 | I415: 其他 | J415: https://www.learnmode.net/course/638732/content | K415: 取自 LearnMode「(112學年) 康軒版─國中數學【八下】」目錄；未找到115學年度明確節名
... A435: 康軒 | B435: 國中 | C435: 7 | D435: 下 | E435: 生物 | F435: 跨科主題 人、植物與環境的共存關係 | G435: 第1節 植物對水土保持的重要性；第2節 植物調節環境的能力 | H435: 115 | I435: 出版商官網 | J435: https://drive.google.com/file/d/1yq-MRrv1k_ECgWgn7AeyBKitIoEDl9if/view | K435: 康軒官網 www.knsh.com.tw/service/plan「國中課程(康軒版)」連結之雲端資料夾檔案「橫式115(二)中自1下三次考查課程計畫.docx」(115學年度課程計畫範本,週次表);章節取自「單元主題」「課程名稱」欄,已略去複習/評量週。自然科學領域第二冊(內容為生物)。
A436: 康軒 | B436: 國中 | C436: 8 | D436: 上 | E436: 理化 | F436: 進入實驗室 | H436: 115 | I436: 出版商官網 | J436: https://drive.google.com/file/d/1CArQh2pOmJ6toIfeLbQEHBq2I3BoeScU/view | K436: 康軒官網 www.knsh.com.tw/service/plan「國中課程(康軒版)」連結之雲端資料夾檔案「橫式115(一)中自2上三次考查課程計畫.docx」(115學年度課程計畫範本,週次表);章節取自「單元主題」「課程名稱」欄,已略去複習/評量週。自然科學領域第三冊(內容為理化)。
A437: 康軒 | B437: 國中 | C437: 8 | D437: 上 | E437: 理化 | F437: 第一章 基本測量 | G437: 1．1 長度與體積的測量；1．2 質量與密度的測量 | H437: 115 | I437: 出版商官網 | J437: https://drive.google.com/file/d/1CArQh2pOmJ6toIfeLbQEHBq2I3BoeScU/view | K437: 康軒官網 www.knsh.com.tw/service/plan「國中課程(康軒版)」連結之雲端資料夾檔案「橫式115(一)中自2上三次考查課程計畫.docx」(115學年度課程計畫範本,週次表);章節取自「單元主題」「課程名稱」欄,已略去複習/評量週。自然科學領域第三冊(內容為理化)。
A438: 康軒 | B438: 國中 | C438: 8 | D438: 上 | E438: 理化 | F438: 第二章 物質的世界 | G438: 2．1 認識物質；2．2 水溶液；2．3 空氣的組成 | H438: 115 | I438: 出版商官網 | J438: https://drive.google.com/file/d/1CArQh2pOmJ6toIfeLbQEHBq2I3BoeScU/view | K438: 康軒官網 www.knsh.com.tw/service/plan「國中課程(康軒版)」連結之雲端資料夾檔案「橫式115(一)中自2上三次考查課程計畫.docx」(115學年度課程計畫範本,週次表);章節取自「單元主題」「課程名稱」欄,已略去複習/評量週。自然科學領域第三冊(內容為理化)。
A439: 康軒 | B439: 國中 | C439: 8 | D439: 上 | E439: 理化 | F439: 跨科主題 物質的分離 | H439: 115 | I439: 出版商官網 | J439: https://drive.google.com/file/d/1CArQh2pOmJ6toIfeLbQEHBq2I3BoeScU/view | K439: 康軒官網 www.knsh.com.tw/service/plan「國中課程(康軒版)」連結之雲端資料夾檔案「橫式115(一)中自2上三次考查課程計畫.docx」(115學年度課程計畫範本,週次表);章節取自「單元主題」「課程名稱」欄,已略去複習/評量週。自然科學領域第三冊(內容為理化)。
A440: 康軒 | B440: 國中 | C440: 8 | D440: 上 | E440: 理化 | F440: 第三章 波動與聲音 | G440: 3．1 波的傳播；3．2 聲波的產生與傳播；3．3 聲波的反射與超聲波；3．4 多變的聲音 | H440: 115 | I440: 出版商官網 | J440: https://drive.google.com/file/d/1CArQh2pOmJ6toIfeLbQEHBq2I3BoeScU/view | K440: 康軒官網 www.knsh.com.tw/service/plan「國中課程(康軒版)」連結之雲端資料夾檔案「橫式115(一)中自2上三次考查課程計畫.docx」(115學年度課程計畫範本,週次表);章節取自「單元主題」「課程名稱」欄,已略去複習/評量週。自然科學領域第三冊(內容為理化)。
A441: 康軒 | B441: 國中 | C441: 8 | D441: 上 | E441: 理化 | F441: 第四章 光 | G441: 4．1 光的傳播與光速；4．2 光的反射與面鏡；4．3 光的折射與透鏡；4．4 光學儀器；4．5 光與顏色 | H441: 115 | I441: 出版商官網 | J441: https://drive.google.com/file/d/1CArQh2pOmJ6toIfeLbQEHBq2I3BoeScU/view | K441: 康軒官網 www.knsh.com.tw/service/plan「國中課程(康軒版)」連結之雲端資料夾檔案「橫式115(一)中自2上三次考查課程計畫.docx」(115學年度課程計畫範本,週次表);章節取自「單元主題」「課程名稱」欄,已略去複習/評量週。自然科學領域第三冊(內容為理化)。
A442: 康軒 | B442: 國中 | C442: 8 | D442: 上 | E442: 理化 | F442: 第五章 溫度與熱 | G442: 5．1 溫度與溫度計；5．2 熱量與比熱；5．3 熱對物質的影響；5．4 熱的傳播方式 | H442: 115 | I442: 出版商官網 | J442: https://drive.google.com/file/d/1CArQh2pOmJ6toIfeLbQEHBq2I3BoeScU/view | K442: 康軒官網 www.knsh.com.tw/service/plan「國中課程(康軒版)」連結之雲端資料夾檔案「橫式115(一)中自2上三次考查課程計畫.docx」(115學年度課程計畫範本,週次表);章節取自「單元主題」「課程名稱」欄,已略去複習/評量週。自然科學領域第三冊(內容為理化)。
A443: 康軒 | B443: 國中 | C443: 8 | D443: 上 | E443: 理化 | F443: 第六章 探索物質組成 | G443: 6．1 元素的探索；6．2 元素週期表；6．3 化合物與原子概念的發展；6．4 分子與化學式 | H443: 115 | I443: 出版商官網 | J443: https://drive.google.com/file/d/1CArQh2pOmJ6toIfeLbQEHBq2I3BoeScU/view | K443: 康軒官網 www.knsh.com.tw/service/plan「國中課程(康軒版)」連結之雲端資料夾檔案「橫式115(一)中自2上三次考查課程計畫.docx」(115學年度課程計畫範本,週次表);章節取自「單元主題」「課程名稱」欄,已略去複習/評量週。自然科學領域第三冊(內容為理化)。
A444: 康軒 | B444: 國中 | C444: 8 | D444: 下 | E444: 理化 | F444: 第一章 化學反應 | G444: 1‧1 質量守恆；1．2 化學反應的微觀世界 | H444: 115 | I444: 出版商官網 | J444: https://drive.google.com/file/d/1Cl4mdSZGlSySqTP7Co1DiiblYrjaAdZN/view | K444: 康軒官網 www.knsh.com.tw/service/plan「國中課程(康軒版)」連結之雲端資料夾檔案「橫式115(二)中自2下三次考查課程計畫.docx」(115學年度課程計畫範本,週次表);章節取自「單元主題」「課程名稱」欄,已略去複習/評量週。自然科學領域第四冊(內容為理化)。
A445: 康軒 | B445: 國中 | C445: 8 | D445: 下 | E445: 理化 | F445: 第二章 氧化與還原 | G445: 2．1 氧化反應；2．2 氧化與還原反應 | H445: 115 | I445: 出版商官網 | J445: https://drive.google.com/file/d/1Cl4mdSZGlSySqTP7Co1DiiblYrjaAdZN/view | K445: 康軒官網 www.knsh.com.tw/service/plan「國中課程(康軒版)」連結之雲端資料夾檔案「橫式115(二)中自2下三次考查課程計畫.docx」(115學年度課程計畫範本,週次表);章節取自「單元主題」「課程名稱」欄,已略去複習/評量週。自然科學領域第四冊(內容為理化)。
...

Sheet 高中
A1: 版本 | B1: 學段 | C1: 年級 | D1: 冊次 | E1: 科目 | F1: 章 | G1: 節 | H1: 學年度 | I1: 來源類型 | J1: 來源網址 | K1: 備註
A2: 南一 | B2: 高中 | C2: 10 | D2: 第一冊 | E2: 國文 | K2: 未查到
A3: 南一 | B3: 高中 | C3: 10 | D3: 第二冊 | E3: 國文 | K3: 未查到
A4: 南一 | B4: 高中 | C4: 11 | D4: 第三冊 | E4: 國文 | K4: 未查到
A5: 南一 | B5: 高中 | C5: 11 | D5: 第四冊 | E5: 國文 | K5: 未查到
A6: 南一 | B6: 高中 | C6: 12 | D6: 第五冊 | E6: 國文 | K6: 未查到
A7: 南一 | B7: 高中 | C7: 12 | D7: 第六冊 | E7: 國文 | K7: 未查到
A8: 南一 | B8: 高中 | D8: 加深加廣選修：各類文學選讀 | E8: 國文 | K8: 未查到
A9: 南一 | B9: 高中 | D9: 加深加廣選修：國學常識 | E9: 國文 | K9: 未查到
A10: 南一 | B10: 高中 | D10: 加深加廣選修：專題閱讀與研究 | E10: 國文 | K10: 未查到
A11: 南一 | B11: 高中 | D11: 加深加廣選修：語文表達及傳播應用 | E11: 國文 | K11: 未查到
A12: 南一 | B12: 高中 | C12: 10 | D12: 第一冊 | E12: 英文 | K12: 未查到
A13: 南一 | B13: 高中 | C13: 10 | D13: 第二冊 | E13: 英文 | K13: 未查到
A14: 南一 | B14: 高中 | C14: 11 | D14: 第三冊 | E14: 英文 | K14: 未查到
A15: 南一 | B15: 高中 | C15: 11 | D15: 第四冊 | E15: 英文 | K15: 未查到
A16: 南一 | B16: 高中 | C16: 12 | D16: 第五冊 | E16: 英文 | K16: 未查到
A17: 南一 | B17: 高中 | C17: 12 | D17: 第六冊 | E17: 英文 | K17: 未查到
A18: 南一 | B18: 高中 | D18: 加深加廣選修：英文閱讀與寫作 | E18: 英文 | K18: 未查到
A19: 南一 | B19: 高中 | D19: 加深加廣選修：英語聽講 | E19: 英文 | K19: 未查到
A20: 南一 | B20: 高中 | C20: 10 | D20: 第一冊 | E20: 數學 | K20: 未查到（南一官方商城有「高中數學(一)課本【114上適用】」商品頁 https://shop.nani1953.com.tw/products/%E9%AB%98%E4%B8%AD%E6%95%B8%E5%AD%B8%E4%B8%80%E8%AA%B2%E6%9C%AC ，但未見目錄）
A21: 南一 | B21: 高中 | C21: 10 | D21: 第二冊 | E21: 數學 | K21: 未查到（南一商城有「高中數學(二)課本【113下適用】」商品頁，未見目錄）
A22: 南一 | B22: 高中 | C22: 11 | D22: 第三冊A | E22: 數學 | K22: 未查到
A23: 南一 | B23: 高中 | C23: 11 | D23: 第三冊B | E23: 數學 | K23: 未查到
A24: 南一 | B24: 高中 | C24: 11 | D24: 第四冊A | E24: 數學 | K24: 未查到
A25: 南一 | B25: 高中 | C25: 11 | D25: 第四冊B | E25: 數學 | K25: 未查到
A26: 南一 | B26: 高中 | C26: 12 | D26: 數學乙上 | E26: 數學 | K26: 未查到
A27: 南一 | B27: 高中 | C27: 12 | D27: 數學乙下 | E27: 數學 | K27: 未查到
A28: 南一 | B28: 高中 | C28: 12 | D28: 數學甲上 | E28: 數學 | K28: 未查到
A29: 南一 | B29: 高中 | C29: 12 | D29: 數學甲下 | E29: 數學 | K29: 未查到（南一商城有「高中選修數學甲下(乙版)課本【114下適用】」商品頁，未見目錄）
A30: 南一 | B30: 高中 | D30: 基礎生物（一） | E30: 生物 | I30: 其他 | K30: 未查到章節；師大附中111學年度資料顯示曾用南一版生物(全)，但沒有單元名稱
A31: 南一 | B31: 高中 | D31: 基礎生物（二） | E31: 生物 | I31: 其他 | K31: 未查到
A32: 南一 | B32: 高中 | D32: 選修生物I | E32: 生物 | I32: 其他 | K32: 未查到章節；師大附中112-2資料顯示曾用南一版選修生物，但沒有單元名稱與冊次
A33: 南一 | B33: 高中 | D33: 選修生物II | E33: 生物 | I33: 其他 | K33: 未查到
A34: 南一 | B34: 高中 | D34: 選修生物III | E34: 生物 | I34: 其他 | K34: 未查到
A35: 南一 | B35: 高中 | D35: 選修生物IV | E35: 生物 | I35: 其他 | K35: 未查到
A36: 南一 | B36: 高中 | D36: 基礎物理（一） | E36: 物理 | I36: 其他 | K36: 未查到
A37: 南一 | B37: 高中 | D37: 選修物理I | E37: 物理 | I37: 其他 | K37: 未查到
A38: 南一 | B38: 高中 | D38: 選修物理II | E38: 物理 | I38: 其他 | K38: 未查到
A39: 南一 | B39: 高中 | D39: 選修物理III | E39: 物理 | I39: 其他 | K39: 未查到
A40: 南一 | B40: 高中 | D40: 選修物理IV | E40: 物理 | I40: 其他 | K40: 未查到
A41: 南一 | B41: 高中 | D41: 選修物理V | E41: 物理 | I41: 其他 | K41: 未查到
A42: 南一 | B42: 高中 | C42: 10 | D42: 高一化學（來源未寫冊名） | E42: 化學 | F42: 物質的組成 | H42: 109 | I42: 學校課程計畫 | J42: https://www.nhush.tp.edu.tw/wp-content/uploads/doc/nhush602/109年度第2學期高一化學.pdf | K42: 南湖高中109學年度第2學期高一化學教學計畫表：「本學期採用南一版化學，內容分物質的組成、物質的形成、物質間的反應、生活中的化學共四大章」；冊名未寫明，章號依列出順序，未列節名；未查到115/114學年度資料；章節文字取自搜尋引擎對來源內容的摘要，請以原檔核對
A43: 南一 | B43: 高中 | C43: 10 | D43: 高一化學（來源未寫冊名） | E43: 化學 | F43: 物質的形成 | H43: 109 | I43: 學校課程計畫 | J43: https://www.nhush.tp.edu.tw/wp-content/uploads/doc/nhush602/109年度第2學期高一化學.pdf | K43: 南湖高中109學年度第2學期高一化學教學計畫表：「本學期採用南一版化學，內容分物質的組成、物質的形成、物質間的反應、生活中的化學共四大章」；冊名未寫明，章號依列出順序，未列節名；未查到115/114學年度資料；章節文字取自搜尋引擎對來源內容的摘要，請以原檔核對
A44: 南一 | B44: 高中 | C44: 10 | D44: 高一化學（來源未寫冊名） | E44: 化學 | F44: 物質間的反應 | H44: 109 | I44: 學校課程計畫 | J44: https://www.nhush.tp.edu.tw/wp-content/uploads/doc/nhush602/109年度第2學期高一化學.pdf | K44: 南湖高中109學年度第2學期高一化學教學計畫表：「本學期採用南一版化學，內容分物質的組成、物質的形成、物質間的反應、生活中的化學共四大章」；冊名未寫明，章號依列出順序，未列節名；未查到115/114學年度資料；章節文字取自搜尋引擎對來源內容的摘要，請以原檔核對
A45: 南一 | B45: 高中 | C45: 10 | D45: 高一化學（來源未寫冊名） | E45: 化學 | F45: 生活中的化學 | H45: 109 | I45: 學校課程計畫 | J45: https://www.nhush.tp.edu.tw/wp-content/uploads/doc/nhush602/109年度第2學期高一化學.pdf | K45: 南湖高中109學年度第2學期高一化學教學計畫表：「本學期採用南一版化學，內容分物質的組成、物質的形成、物質間的反應、生活中的化學共四大章」；冊名未寫明，章號依列出順序，未列節名；未查到115/114學年度資料；章節文字取自搜尋引擎對來源內容的摘要，請以原檔核對
A46: 南一 | B46: 高中 | C46: 12 | D46: 選修化學V（來源只寫「選修化學」） | E46: 化學 | F46: 第1章（章名未見） | G46: 1-1 烴類；1-2 有機鹵化物；1-3 醇、酚、醚；1-4、1-5 醛、酮、酸、酯（來源合列）；1-6 胺與醯胺 | H46: 111 | I46: 學校課程計畫 | J46: https://www.hs.ntnu.edu.tw/static/webroot/G162269151451663/application/NW167904652851841.pdf | K46: 師大附中111學年度第2學期高三化學進度表，課程名稱：選修化學，教科書版本：南一；來源沒有寫冊次，依內容（有機、聚合物）歸入選修化學V，請核實；章名未見；摘要只到第6週；未查到115/114學年度資料；章節文字取自搜尋引擎對來源內容的摘要，請以原檔核對
A47: 南一 | B47: 高中 | C47: 12 | D47: 選修化學V（來源只寫「選修化學」） | E47: 化學 | F47: 第2章（章名未見） | G47: 2-1 聚合物分類；2-2 天然聚合物 | H47: 111 | I47: 學校課程計畫 | J47: https://www.hs.ntnu.edu.tw/static/webroot/G162269151451663/application/NW167904652851841.pdf | K47: 師大附中111學年度第2學期高三化學進度表，課程名稱：選修化學，教科書版本：南一；來源沒有寫冊次，依內容（有機、聚合物）歸入選修化學V，請核實；章名未見；摘要只到第6週；未查到115/114學年度資料；章節文字取自搜尋引擎對來源內容的摘要，請以原檔核對
A48: 南一 | B48: 高中 | D48: 基礎化學（三） | E48: 化學 | I48: 其他 | K48: 未查到
A49: 南一 | B49: 高中 | D49: 基礎化學（二） | E49: 化學 | I49: 其他 | K49: 未查到
A50: 南一 | B50: 高中 | D50: 選修化學I | E50: 化學 | I50: 其他 | K50: 未查到
A51: 南一 | B51: 高中 | D51: 選修化學II | E51: 化學 | I51: 其他 | K51: 未查到
A52: 南一 | B52: 高中 | D52: 選修化學III | E52: 化學 | I52: 其他 | K52: 未查到
A53: 南一 | B53: 高中 | D53: 選修化學IV | E53: 化學 | I53: 其他 | K53: 未查到
A54: 南一 | B54: 高中 | D54: 基礎地球科學（一） | E54: 地球科學 | I54: 其他 | K54: 未查到
A55: 南一 | B55: 高中 | D55: 基礎地球科學（二） | E55: 地球科學 | I55: 其他 | K55: 未查到
A56: 南一 | B56: 高中 | D56: 選修地球科學I | E56: 地球科學 | I56: 其他 | K56: 未查到
A57: 南一 | B57: 高中 | D57: 選修地球科學II | E57: 地球科學 | I57: 其他 | K57: 未查到
A58: 南一 | B58: 高中 | D58: 選修地球科學III | E58: 地球科學 | I58: 其他 | K58: 未查到
A59: 南一 | B59: 高中 | D59: 選修地球科學IV | E59: 地球科學 | I59: 其他 | K59: 未查到
A60: 南一 | B60: 高中 | C60: 10 | D60: 第一冊 | E60: 歷史 | K60: 未查到（WebSearch 額度用盡，未及搜尋）
A61: 南一 | B61: 高中 | C61: 10 | D61: 第二冊 | E61: 歷史 | K61: 未查到（WebSearch 額度用盡，未及搜尋）
A62: 南一 | B62: 高中 | C62: 11 | D62: 第三冊 | E62: 歷史 | K62: 未查到（WebSearch 額度用盡，未及搜尋）
A63: 南一 | B63: 高中 | D63: 加深加廣選修 探究與實作：歷史學探究 | E63: 歷史 | K63: 未查到（WebSearch 額度用盡，未及搜尋）
A64: 南一 | B64: 高中 | D64: 加深加廣選修 族群、性別與國家的歷史 | E64: 歷史 | K64: 未查到（WebSearch 額度用盡，未及搜尋）
A65: 南一 | B65: 高中 | D65: 加深加廣選修 科技、環境與藝術的歷史 | E65: 歷史 | K65: 未查到（WebSearch 額度用盡，未及搜尋）
A66: 南一 | B66: 高中 | C66: 10 | D66: 第一冊 | E66: 地理 | K66: 未查到（WebSearch 額度用盡，未及搜尋）
A67: 南一 | B67: 高中 | C67: 10 | D67: 第二冊 | E67: 地理 | K67: 未查到（WebSearch 額度用盡，未及搜尋）
A68: 南一 | B68: 高中 | C68: 11 | D68: 第三冊 | E68: 地理 | K68: 未查到（WebSearch 額度用盡，未及搜尋）
A69: 南一 | B69: 高中 | D69: 加深加廣選修 探究與實作：地理與人文社會科學研究 | E69: 地理 | K69: 未查到（WebSearch 額度用盡，未及搜尋）
A70: 南一 | B70: 高中 | D70: 加深加廣選修 社會環境議題 | E70: 地理 | K70: 未查到（WebSearch 額度用盡，未及搜尋）
A71: 南一 | B71: 高中 | D71: 加深加廣選修 空間資訊科技 | E71: 地理 | K71: 未查到（WebSearch 額度用盡，未及搜尋）
A72: 南一 | B72: 高中 | C72: 10 | D72: 第一冊 | E72: 公民與社會 | K72: 未查到（WebSearch 額度用盡，未及搜尋）
A73: 南一 | B73: 高中 | C73: 10 | D73: 第二冊 | E73: 公民與社會 | K73: 未查到（WebSearch 額度用盡，未及搜尋）
A74: 南一 | B74: 高中 | C74: 11 | D74: 第三冊 | E74: 公民與社會 | K74: 未查到（WebSearch 額度用盡，未及搜尋）
A75: 南一 | B75: 高中 | D75: 加深加廣選修 探究與實作：公共議題與社會探究 | E75: 公民與社會 | K75: 未查到（WebSearch 額度用盡，未及搜尋）
A76: 南一 | B76: 高中 | D76: 加深加廣選修 民主政治與法律 | E76: 公民與社會 | K76: 未查到（WebSearch 額度用盡，未及搜尋）
A77: 南一 | B77: 高中 | D77: 加深加廣選修 現代社會與經濟 | E77: 公民與社會 | K77: 未查到（WebSearch 額度用盡，未及搜尋）
A78: 三民 | B78: 高中 | C78: 10 | D78: 第一冊 | E78: 國文 | K78: 未查到
A79: 三民 | B79: 高中 | C79: 10 | D79: 第二冊 | E79: 國文 | K79: 未查到
A80: 三民 | B80: 高中 | C80: 11 | D80: 第三冊 | E80: 國文 | K80: 未查到
A81: 三民 | B81: 高中 | C81: 11 | D81: 第四冊 | E81: 國文 | K81: 未查到
A82: 三民 | B82: 高中 | C82: 12 | D82: 第五冊 | E82: 國文 | K82: 未查到
A83: 三民 | B83: 高中 | C83: 12 | D83: 第六冊 | E83: 國文 | K83: 未查到
A84: 三民 | B84: 高中 | D84: 加深加廣選修：各類文學選讀 | E84: 國文 | K84: 未查到
A85: 三民 | B85: 高中 | D85: 加深加廣選修：國學常識 | E85: 國文 | K85: 未查到
A86: 三民 | B86: 高中 | D86: 加深加廣選修：專題閱讀與研究 | E86: 國文 | K86: 未查到
A87: 三民 | B87: 高中 | D87: 加深加廣選修：語文表達及傳播應用 | E87: 國文 | K87: 未查到
A88: 三民 | B88: 高中 | C88: 10 | D88: 第一冊 | E88: 英文 | K88: 未查到
A89: 三民 | B89: 高中 | C89: 10 | D89: 第二冊 | E89: 英文 | K89: 未查到
A90: 三民 | B90: 高中 | C90: 11 | D90: 第三冊 | E90: 英文 | K90: 未查到
A91: 三民 | B91: 高中 | C91: 11 | D91: 第四冊 | E91: 英文 | K91: 未查到
A92: 三民 | B92: 高中 | C92: 12 | D92: 第五冊 | E92: 英文 | K92: 未查到
A93: 三民 | B93: 高中 | C93: 12 | D93: 第六冊 | E93: 英文 | K93: 未查到
A94: 三民 | B94: 高中 | D94: 加深加廣選修：英文閱讀與寫作 | E94: 英文 | K94: 未查到
A95: 三民 | B95: 高中 | D95: 加深加廣選修：英語聽講 | E95: 英文 | K95: 未查到
A96: 三民 | B96: 高中 | C96: 10 | D96: 第一冊 | E96: 數學 | F96: 第1章 數與式 | G96: 實數；絕對值；式的運算；指數與對數 | H96: 未標示 | I96: 書店頁面 | J96: https://www.sanmin.com.tw/product/index/013368794 | K96: 取自三民網路書店配套書（普通型高中數學第一冊實力習作）商品頁目次，配合三民（鄭惟厚主編）課本編寫；節號未於摘要中逐一列出，僅列節名；較早（2019）教學講義版2-2作「二元一次方程式與不等式」
A97: 三民 | B97: 高中 | C97: 10 | D97: 第一冊 | E97: 數學 | F97: 第2章 直線與圓 | G97: 直線方程式；直線方程式的應用；圓與直線的關係 | H97: 未標示 | I97: 書店頁面 | J97: https://www.sanmin.com.tw/product/index/013368794 | K97: 取自三民網路書店配套書（普通型高中數學第一冊實力習作）商品頁目次，配合三民（鄭惟厚主編）課本編寫；節號未於摘要中逐一列出，僅列節名；較早（2019）教學講義版2-2作「二元一次方程式與不等式」
A98: 三民 | B98: 高中 | C98: 10 | D98: 第一冊 | E98: 數學 | F98: 第3章 多項式函數 | G98: 多項式及其運算；簡單多項式函數及其圖形；多項式不等式 | H98: 未標示 | I98: 書店頁面 | J98: https://www.sanmin.com.tw/product/index/013368794 | K98: 取自三民網路書店配套書（普通型高中數學第一冊實力習作）商品頁目次，配合三民（鄭惟厚主編）課本編寫；節號未於摘要中逐一列出，僅列節名；較早（2019）教學講義版2-2作「二元一次方程式與不等式」
A99: 三民 | B99: 高中 | C99: 10 | D99: 第二冊 | E99: 數學 | F99: 第1章 三角 | G99: 1-1 直角三角形的三角比；1-2 廣義角與極座標；1-3 正弦定理與餘弦定理 | H99: 未標示 | I99: 書店頁面 | J99: https://www.sanmin.com.tw/product/index/007588879 | K99: 取自三民網路書店配套書（普通型高中數學第二冊習作，2020/02/01）商品頁目次，配合三民（鄭惟厚主編）課本編寫；2024、2026年另有新版配套書，目次未見
A100: 三民 | B100: 高中 | C100: 10 | D100: 第二冊 | E100: 數學 | F100: 第2章 數列與級數 | G100: 2-1 數列與遞迴關係；2-2 級數 | H100: 未標示 | I100: 書店頁面 | J100: https://www.sanmin.com.tw/product/index/007588879 | K100: 取自三民網路書店配套書（普通型高中數學第二冊習作，2020/02/01）商品頁目次，配合三民（鄭惟厚主編）課本編寫；2024、2026年另有新版配套書，目次未見
...

Sheet 涵蓋總覽
A1: 學段 | B1: 版本 | C1: 科目 | D1: 年級 | E1: 冊次 | F1: 已查到章（課）數 | G1: 狀態
A2: 國中 | B2: 翰林 | C2: 國文 | D2: 7 | E2: 上 | F2: =COUNTIFS(國中!$A:$A,$B2,國中!$E:$E,$C2,國中!$F:$F,"<>",國中!$C:$C,$D2,國中!$D:$D,$E2) | G2: =IF(F2>0,"已查到","未查到")
A3: 國中 | B3: 翰林 | C3: 國文 | D3: 7 | E3: 下 | F3: =COUNTIFS(國中!$A:$A,$B3,國中!$E:$E,$C3,國中!$F:$F,"<>",國中!$C:$C,$D3,國中!$D:$D,$E3) | G3: =IF(F3>0,"已查到","未查到")
A4: 國中 | B4: 翰林 | C4: 國文 | D4: 8 | E4: 上 | F4: =COUNTIFS(國中!$A:$A,$B4,國中!$E:$E,$C4,國中!$F:$F,"<>",國中!$C:$C,$D4,國中!$D:$D,$E4) | G4: =IF(F4>0,"已查到","未查到")
A5: 國中 | B5: 翰林 | C5: 國文 | D5: 8 | E5: 下 | F5: =COUNTIFS(國中!$A:$A,$B5,國中!$E:$E,$C5,國中!$F:$F,"<>",國中!$C:$C,$D5,國中!$D:$D,$E5) | G5: =IF(F5>0,"已查到","未查到")
A6: 國中 | B6: 翰林 | C6: 國文 | D6: 9 | E6: 上 | F6: =COUNTIFS(國中!$A:$A,$B6,國中!$E:$E,$C6,國中!$F:$F,"<>",國中!$C:$C,$D6,國中!$D:$D,$E6) | G6: =IF(F6>0,"已查到","未查到")
A7: 國中 | B7: 翰林 | C7: 國文 | D7: 9 | E7: 下 | F7: =COUNTIFS(國中!$A:$A,$B7,國中!$E:$E,$C7,國中!$F:$F,"<>",國中!$C:$C,$D7,國中!$D:$D,$E7) | G7: =IF(F7>0,"已查到","未查到")
A8: 國中 | B8: 翰林 | C8: 英文 | D8: 7 | E8: 上 | F8: =COUNTIFS(國中!$A:$A,$B8,國中!$E:$E,$C8,國中!$F:$F,"<>",國中!$C:$C,$D8,國中!$D:$D,$E8) | G8: =IF(F8>0,"已查到","未查到")
A9: 國中 | B9: 翰林 | C9: 英文 | D9: 7 | E9: 下 | F9: =COUNTIFS(國中!$A:$A,$B9,國中!$E:$E,$C9,國中!$F:$F,"<>",國中!$C:$C,$D9,國中!$D:$D,$E9) | G9: =IF(F9>0,"已查到","未查到")
A10: 國中 | B10: 翰林 | C10: 英文 | D10: 8 | E10: 上 | F10: =COUNTIFS(國中!$A:$A,$B10,國中!$E:$E,$C10,國中!$F:$F,"<>",國中!$C:$C,$D10,國中!$D:$D,$E10) | G10: =IF(F10>0,"已查到","未查到")
A11: 國中 | B11: 翰林 | C11: 英文 | D11: 8 | E11: 下 | F11: =COUNTIFS(國中!$A:$A,$B11,國中!$E:$E,$C11,國中!$F:$F,"<>",國中!$C:$C,$D11,國中!$D:$D,$E11) | G11: =IF(F11>0,"已查到","未查到")
A12: 國中 | B12: 翰林 | C12: 英文 | D12: 9 | E12: 上 | F12: =COUNTIFS(國中!$A:$A,$B12,國中!$E:$E,$C12,國中!$F:$F,"<>",國中!$C:$C,$D12,國中!$D:$D,$E12) | G12: =IF(F12>0,"已查到","未查到")
A13: 國中 | B13: 翰林 | C13: 英文 | D13: 9 | E13: 下 | F13: =COUNTIFS(國中!$A:$A,$B13,國中!$E:$E,$C13,國中!$F:$F,"<>",國中!$C:$C,$D13,國中!$D:$D,$E13) | G13: =IF(F13>0,"已查到","未查到")
... A95: 國中 | B95: 南一 | C95: 國文 | D95: 9 | E95: 下 | F95: =COUNTIFS(國中!$A:$A,$B95,國中!$E:$E,$C95,國中!$F:$F,"<>",國中!$C:$C,$D95,國中!$D:$D,$E95) | G95: =IF(F95>0,"已查到","未查到")
A96: 高中 | B96: 南一 | C96: 國文 | D96: 10 | E96: 第一冊 | F96: =COUNTIFS(高中!$A:$A,$B96,高中!$E:$E,$C96,高中!$F:$F,"<>",高中!$C:$C,$D96,高中!$D:$D,$E96) | G96: =IF(F96>0,"已查到","未查到")
A97: 高中 | B97: 南一 | C97: 國文 | D97: 10 | E97: 第二冊 | F97: =COUNTIFS(高中!$A:$A,$B97,高中!$E:$E,$C97,高中!$F:$F,"<>",高中!$C:$C,$D97,高中!$D:$D,$E97) | G97: =IF(F97>0,"已查到","未查到")
A98: 高中 | B98: 南一 | C98: 國文 | D98: 11 | E98: 第三冊 | F98: =COUNTIFS(高中!$A:$A,$B98,高中!$E:$E,$C98,高中!$F:$F,"<>",高中!$C:$C,$D98,高中!$D:$D,$E98) | G98: =IF(F98>0,"已查到","未查到")
A99: 高中 | B99: 南一 | C99: 國文 | D99: 11 | E99: 第四冊 | F99: =COUNTIFS(高中!$A:$A,$B99,高中!$E:$E,$C99,高中!$F:$F,"<>",高中!$C:$C,$D99,高中!$D:$D,$E99) | G99: =IF(F99>0,"已查到","未查到")
A100: 高中 | B100: 南一 | C100: 國文 | D100: 12 | E100: 第五冊 | F100: =COUNTIFS(高中!$A:$A,$B100,高中!$E:$E,$C100,高中!$F:$F,"<>",高中!$C:$C,$D100,高中!$D:$D,$E100) | G100: =IF(F100>0,"已查到","未查到")
A101: 高中 | B101: 南一 | C101: 國文 | D101: 12 | E101: 第六冊 | F101: =COUNTIFS(高中!$A:$A,$B101,高中!$E:$E,$C101,高中!$F:$F,"<>",高中!$C:$C,$D101,高中!$D:$D,$E101) | G101: =IF(F101>0,"已查到","未查到")
A102: 高中 | B102: 南一 | C102: 國文 | E102: 加深加廣選修：各類文學選讀 | F102: =COUNTIFS(高中!$A:$A,$B102,高中!$E:$E,$C102,高中!$F:$F,"<>",高中!$C:$C,"",高中!$D:$D,$E102) | G102: =IF(F102>0,"已查到","未查到")
A103: 高中 | B103: 南一 | C103: 國文 | E103: 加深加廣選修：國學常識 | F103: =COUNTIFS(高中!$A:$A,$B103,高中!$E:$E,$C103,高中!$F:$F,"<>",高中!$C:$C,"",高中!$D:$D,$E103) | G103: =IF(F103>0,"已查到","未查到")
A104: 高中 | B104: 南一 | C104: 國文 | E104: 加深加廣選修：專題閱讀與研究 | F104: =COUNTIFS(高中!$A:$A,$B104,高中!$E:$E,$C104,高中!$F:$F,"<>",高中!$C:$C,"",高中!$D:$D,$E104) | G104: =IF(F104>0,"已查到","未查到")
A105: 高中 | B105: 南一 | C105: 國文 | E105: 加深加廣選修：語文表達及傳播應用 | F105: =COUNTIFS(高中!$A:$A,$B105,高中!$E:$E,$C105,高中!$F:$F,"<>",高中!$C:$C,"",高中!$D:$D,$E105) | G105: =IF(F105>0,"已查到","未查到")
A106: 國中 | B106: 南一 | C106: 英文 | D106: 7 | E106: 上 | F106: =COUNTIFS(國中!$A:$A,$B106,國中!$E:$E,$C106,國中!$F:$F,"<>",國中!$C:$C,$D106,國中!$D:$D,$E106) | G106: =IF(F106>0,"已查到","未查到")
A107: 國中 | B107: 南一 | C107: 英文 | D107: 7 | E107: 下 | F107: =COUNTIFS(國中!$A:$A,$B107,國中!$E:$E,$C107,國中!$F:$F,"<>",國中!$C:$C,$D107,國中!$D:$D,$E107) | G107: =IF(F107>0,"已查到","未查到")
A108: 國中 | B108: 南一 | C108: 英文 | D108: 8 | E108: 上 | F108: =COUNTIFS(國中!$A:$A,$B108,國中!$E:$E,$C108,國中!$F:$F,"<>",國中!$C:$C,$D108,國中!$D:$D,$E108) | G108: =IF(F108>0,"已查到","未查到")
A109: 國中 | B109: 南一 | C109: 英文 | D109: 8 | E109: 下 | F109: =COUNTIFS(國中!$A:$A,$B109,國中!$E:$E,$C109,國中!$F:$F,"<>",國中!$C:$C,$D109,國中!$D:$D,$E109) | G109: =IF(F109>0,"已查到","未查到")
A110: 國中 | B110: 南一 | C110: 英文 | D110: 9 | E110: 上 | F110: =COUNTIFS(國中!$A:$A,$B110,國中!$E:$E,$C110,國中!$F:$F,"<>",國中!$C:$C,$D110,國中!$D:$D,$E110) | G110: =IF(F110>0,"已查到","未查到")
A111: 國中 | B111: 南一 | C111: 英文 | D111: 9 | E111: 下 | F111: =COUNTIFS(國中!$A:$A,$B111,國中!$E:$E,$C111,國中!$F:$F,"<>",國中!$C:$C,$D111,國中!$D:$D,$E111) | G111: =IF(F111>0,"已查到","未查到")
A112: 高中 | B112: 南一 | C112: 英文 | D112: 10 | E112: 第一冊 | F112: =COUNTIFS(高中!$A:$A,$B112,高中!$E:$E,$C112,高中!$F:$F,"<>",高中!$C:$C,$D112,高中!$D:$D,$E112) | G112: =IF(F112>0,"已查到","未查到")
A113: 高中 | B113: 南一 | C113: 英文 | D113: 10 | E113: 第二冊 | F113: =COUNTIFS(高中!$A:$A,$B113,高中!$E:$E,$C113,高中!$F:$F,"<>",高中!$C:$C,$D113,高中!$D:$D,$E113) | G113: =IF(F113>0,"已查到","未查到")
A114: 高中 | B114: 南一 | C114: 英文 | D114: 11 | E114: 第三冊 | F114: =COUNTIFS(高中!$A:$A,$B114,高中!$E:$E,$C114,高中!$F:$F,"<>",高中!$C:$C,$D114,高中!$D:$D,$E114) | G114: =IF(F114>0,"已查到","未查到")
A115: 高中 | B115: 南一 | C115: 英文 | D115: 11 | E115: 第四冊 | F115: =COUNTIFS(高中!$A:$A,$B115,高中!$E:$E,$C115,高中!$F:$F,"<>",高中!$C:$C,$D115,高中!$D:$D,$E115) | G115: =IF(F115>0,"已查到","未查到")
A116: 高中 | B116: 南一 | C116: 英文 | D116: 12 | E116: 第五冊 | F116: =COUNTIFS(高中!$A:$A,$B116,高中!$E:$E,$C116,高中!$F:$F,"<>",高中!$C:$C,$D116,高中!$D:$D,$E116) | G116: =IF(F116>0,"已查到","未查到")
A117: 高中 | B117: 南一 | C117: 英文 | D117: 12 | E117: 第六冊 | F117: =COUNTIFS(高中!$A:$A,$B117,高中!$E:$E,$C117,高中!$F:$F,"<>",高中!$C:$C,$D117,高中!$D:$D,$E117) | G117: =IF(F117>0,"已查到","未查到")
A118: 高中 | B118: 南一 | C118: 英文 | E118: 加深加廣選修：英文閱讀與寫作 | F118: =COUNTIFS(高中!$A:$A,$B118,高中!$E:$E,$C118,高中!$F:$F,"<>",高中!$C:$C,"",高中!$D:$D,$E118) | G118: =IF(F118>0,"已查到","未查到")
A119: 高中 | B119: 南一 | C119: 英文 | E119: 加深加廣選修：英語聽講 | F119: =COUNTIFS(高中!$A:$A,$B119,高中!$E:$E,$C119,高中!$F:$F,"<>",高中!$C:$C,"",高中!$D:$D,$E119) | G119: =IF(F119>0,"已查到","未查到")
A120: 國中 | B120: 南一 | C120: 數學 | D120: 7 | E120: 上 | F120: =COUNTIFS(國中!$A:$A,$B120,國中!$E:$E,$C120,國中!$F:$F,"<>",國中!$C:$C,$D120,國中!$D:$D,$E120) | G120: =IF(F120>0,"已查到","未查到")
A121: 國中 | B121: 南一 | C121: 數學 | D121: 7 | E121: 下 | F121: =COUNTIFS(國中!$A:$A,$B121,國中!$E:$E,$C121,國中!$F:$F,"<>",國中!$C:$C,$D121,國中!$D:$D,$E121) | G121: =IF(F121>0,"已查到","未查到")
A122: 國中 | B122: 南一 | C122: 數學 | D122: 8 | E122: 上 | F122: =COUNTIFS(國中!$A:$A,$B122,國中!$E:$E,$C122,國中!$F:$F,"<>",國中!$C:$C,$D122,國中!$D:$D,$E122) | G122: =IF(F122>0,"已查到","未查到")
A123: 國中 | B123: 南一 | C123: 數學 | D123: 8 | E123: 下 | F123: =COUNTIFS(國中!$A:$A,$B123,國中!$E:$E,$C123,國中!$F:$F,"<>",國中!$C:$C,$D123,國中!$D:$D,$E123) | G123: =IF(F123>0,"已查到","未查到")
A124: 國中 | B124: 南一 | C124: 數學 | D124: 9 | E124: 上 | F124: =COUNTIFS(國中!$A:$A,$B124,國中!$E:$E,$C124,國中!$F:$F,"<>",國中!$C:$C,$D124,國中!$D:$D,$E124) | G124: =IF(F124>0,"已查到","未查到")
A125: 國中 | B125: 南一 | C125: 數學 | D125: 9 | E125: 下 | F125: =COUNTIFS(國中!$A:$A,$B125,國中!$E:$E,$C125,國中!$F:$F,"<>",國中!$C:$C,$D125,國中!$D:$D,$E125) | G125: =IF(F125>0,"已查到","未查到")
A126: 高中 | B126: 南一 | C126: 數學 | D126: 10 | E126: 第一冊 | F126: =COUNTIFS(高中!$A:$A,$B126,高中!$E:$E,$C126,高中!$F:$F,"<>",高中!$C:$C,$D126,高中!$D:$D,$E126) | G126: =IF(F126>0,"已查到","未查到")
A127: 高中 | B127: 南一 | C127: 數學 | D127: 10 | E127: 第二冊 | F127: =COUNTIFS(高中!$A:$A,$B127,高中!$E:$E,$C127,高中!$F:$F,"<>",高中!$C:$C,$D127,高中!$D:$D,$E127) | G127: =IF(F127>0,"已查到","未查到")
A128: 高中 | B128: 南一 | C128: 數學 | D128: 11 | E128: 第三冊A | F128: =COUNTIFS(高中!$A:$A,$B128,高中!$E:$E,$C128,高中!$F:$F,"<>",高中!$C:$C,$D128,高中!$D:$D,$E128) | G128: =IF(F128>0,"已查到","未查到")
A129: 高中 | B129: 南一 | C129: 數學 | D129: 11 | E129: 第三冊B | F129: =COUNTIFS(高中!$A:$A,$B129,高中!$E:$E,$C129,高中!$F:$F,"<>",高中!$C:$C,$D129,高中!$D:$D,$E129) | G129: =IF(F129>0,"已查到","未查到")
A130: 高中 | B130: 南一 | C130: 數學 | D130: 11 | E130: 第四冊A | F130: =COUNTIFS(高中!$A:$A,$B130,高中!$E:$E,$C130,高中!$F:$F,"<>",高中!$C:$C,$D130,高中!$D:$D,$E130) | G130: =IF(F130>0,"已查到","未查到")
A131: 高中 | B131: 南一 | C131: 數學 | D131: 11 | E131: 第四冊B | F131: =COUNTIFS(高中!$A:$A,$B131,高中!$E:$E,$C131,高中!$F:$F,"<>",高中!$C:$C,$D131,高中!$D:$D,$E131) | G131: =IF(F131>0,"已查到","未查到")
A132: 高中 | B132: 南一 | C132: 數學 | D132: 12 | E132: 數學乙上 | F132: =COUNTIFS(高中!$A:$A,$B132,高中!$E:$E,$C132,高中!$F:$F,"<>",高中!$C:$C,$D132,高中!$D:$D,$E132) | G132: =IF(F132>0,"已查到","未查到")
A133: 高中 | B133: 南一 | C133: 數學 | D133: 12 | E133: 數學乙下 | F133: =COUNTIFS(高中!$A:$A,$B133,高中!$E:$E,$C133,高中!$F:$F,"<>",高中!$C:$C,$D133,高中!$D:$D,$E133) | G133: =IF(F133>0,"已查到","未查到")
A134: 高中 | B134: 南一 | C134: 數學 | D134: 12 | E134: 數學甲上 | F134: =COUNTIFS(高中!$A:$A,$B134,高中!$E:$E,$C134,高中!$F:$F,"<>",高中!$C:$C,$D134,高中!$D:$D,$E134) | G134: =IF(F134>0,"已查到","未查到")
A135: 高中 | B135: 南一 | C135: 數學 | D135: 12 | E135: 數學甲下 | F135: =COUNTIFS(高中!$A:$A,$B135,高中!$E:$E,$C135,高中!$F:$F,"<>",高中!$C:$C,$D135,高中!$D:$D,$E135) | G135: =IF(F135>0,"已查到","未查到")
A136: 國中 | B136: 南一 | C136: 生物 | D136: 7 | E136: 上 | F136: =COUNTIFS(國中!$A:$A,$B136,國中!$E:$E,$C136,國中!$F:$F,"<>",國中!$C:$C,$D136,國中!$D:$D,$E136) | G136: =IF(F136>0,"已查到","未查到")
A137: 國中 | B137: 南一 | C137: 生物 | D137: 7 | E137: 下 | F137: =COUNTIFS(國中!$A:$A,$B137,國中!$E:$E,$C137,國中!$F:$F,"<>",國中!$C:$C,$D137,國中!$D:$D,$E137) | G137: =IF(F137>0,"已查到","未查到")
A138: 高中 | B138: 南一 | C138: 生物 | E138: 基礎生物（一） | F138: =COUNTIFS(高中!$A:$A,$B138,高中!$E:$E,$C138,高中!$F:$F,"<>",高中!$C:$C,"",高中!$D:$D,$E138) | G138: =IF(F138>0,"已查到","未查到")
A139: 高中 | B139: 南一 | C139: 生物 | E139: 基礎生物（二） | F139: =COUNTIFS(高中!$A:$A,$B139,高中!$E:$E,$C139,高中!$F:$F,"<>",高中!$C:$C,"",高中!$D:$D,$E139) | G139: =IF(F139>0,"已查到","未查到")
A140: 高中 | B140: 南一 | C140: 生物 | E140: 選修生物I | F140: =COUNTIFS(高中!$A:$A,$B140,高中!$E:$E,$C140,高中!$F:$F,"<>",高中!$C:$C,"",高中!$D:$D,$E140) | G140: =IF(F140>0,"已查到","未查到")
A141: 高中 | B141: 南一 | C141: 生物 | E141: 選修生物II | F141: =COUNTIFS(高中!$A:$A,$B141,高中!$E:$E,$C141,高中!$F:$F,"<>",高中!$C:$C,"",高中!$D:$D,$E141) | G141: =IF(F141>0,"已查到","未查到")
A142: 高中 | B142: 南一 | C142: 生物 | E142: 選修生物III | F142: =COUNTIFS(高中!$A:$A,$B142,高中!$E:$E,$C142,高中!$F:$F,"<>",高中!$C:$C,"",高中!$D:$D,$E142) | G142: =IF(F142>0,"已查到","未查到")
A143: 高中 | B143: 南一 | C143: 生物 | E143: 選修生物IV | F143: =COUNTIFS(高中!$A:$A,$B143,高中!$E:$E,$C143,高中!$F:$F,"<>",高中!$C:$C,"",高中!$D:$D,$E143) | G143: =IF(F143>0,"已查到","未查到")
A144: 國中 | B144: 南一 | C144: 理化 | D144: 8 | E144: 上 | F144: =COUNTIFS(國中!$A:$A,$B144,國中!$E:$E,$C144,國中!$F:$F,"<>",國中!$C:$C,$D144,國中!$D:$D,$E144) | G144: =IF(F144>0,"已查到","未查到")
A145: 國中 | B145: 南一 | C145: 理化 | D145: 8 | E145: 下 | F145: =COUNTIFS(國中!$A:$A,$B145,國中!$E:$E,$C145,國中!$F:$F,"<>",國中!$C:$C,$D145,國中!$D:$D,$E145) | G145: =IF(F145>0,"已查到","未查到")
A146: 國中 | B146: 南一 | C146: 理化 | D146: 9 | E146: 上 | F146: =COUNTIFS(國中!$A:$A,$B146,國中!$E:$E,$C146,國中!$F:$F,"<>",國中!$C:$C,$D146,國中!$D:$D,$E146) | G146: =IF(F146>0,"已查到","未查到")
A147: 國中 | B147: 南一 | C147: 理化 | D147: 9 | E147: 下 | F147: =COUNTIFS(國中!$A:$A,$B147,國中!$E:$E,$C147,國中!$F:$F,"<>",國中!$C:$C,$D147,國中!$D:$D,$E147) | G147: =IF(F147>0,"已查到","未查到")
A148: 高中 | B148: 南一 | C148: 物理 | E148: 基礎物理（一） | F148: =COUNTIFS(高中!$A:$A,$B148,高中!$E:$E,$C148,高中!$F:$F,"<>",高中!$C:$C,"",高中!$D:$D,$E148) | G148: =IF(F148>0,"已查到","未查到")
A149: 高中 | B149: 南一 | C149: 物理 | E149: 選修物理I | F149: =COUNTIFS(高中!$A:$A,$B149,高中!$E:$E,$C149,高中!$F:$F,"<>",高中!$C:$C,"",高中!$D:$D,$E149) | G149: =IF(F149>0,"已查到","未查到")
A150: 高中 | B150: 南一 | C150: 物理 | E150: 選修物理II | F150: =COUNTIFS(高中!$A:$A,$B150,高中!$E:$E,$C150,高中!$F:$F,"<>",高中!$C:$C,"",高中!$D:$D,$E150) | G150: =IF(F150>0,"已查到","未查到")
A151: 高中 | B151: 南一 | C151: 物理 | E151: 選修物理III | F151: =COUNTIFS(高中!$A:$A,$B151,高中!$E:$E,$C151,高中!$F:$F,"<>",高中!$C:$C,"",高中!$D:$D,$E151) | G151: =IF(F151>0,"已查到","未查到")
A152: 高中 | B152: 南一 | C152: 物理 | E152: 選修物理IV | F152: =COUNTIFS(高中!$A:$A,$B152,高中!$E:$E,$C152,高中!$F:$F,"<>",高中!$C:$C,"",高中!$D:$D,$E152) | G152: =IF(F152>0,"已查到","未查到")
A153: 高中 | B153: 南一 | C153: 物理 | E153: 選修物理V | F153: =COUNTIFS(高中!$A:$A,$B153,高中!$E:$E,$C153,高中!$F:$F,"<>",高中!$C:$C,"",高中!$D:$D,$E153) | G153: =IF(F153>0,"已查到","未查到")
A154: 高中 | B154: 南一 | C154: 化學 | D154: 10 | E154: 高一化學（來源未寫冊名） | F154: =COUNTIFS(高中!$A:$A,$B154,高中!$E:$E,$C154,高中!$F:$F,"<>",高中!$C:$C,$D154,高中!$D:$D,$E154) | G154: =IF(F154>0,"已查到","未查到")
A155: 高中 | B155: 南一 | C155: 化學 | D155: 12 | E155: 選修化學V（來源只寫「選修化學」） | F155: =COUNTIFS(高中!$A:$A,$B155,高中!$E:$E,$C155,高中!$F:$F,"<>",高中!$C:$C,$D155,高中!$D:$D,$E155) | G155: =IF(F155>0,"已查到","未查到")
A156: 高中 | B156: 南一 | C156: 化學 | E156: 基礎化學（三） | F156: =COUNTIFS(高中!$A:$A,$B156,高中!$E:$E,$C156,高中!$F:$F,"<>",高中!$C:$C,"",高中!$D:$D,$E156) | G156: =IF(F156>0,"已查到","未查到")
A157: 高中 | B157: 南一 | C157: 化學 | E157: 基礎化學（二） | F157: =COUNTIFS(高中!$A:$A,$B157,高中!$E:$E,$C157,高中!$F:$F,"<>",高中!$C:$C,"",高中!$D:$D,$E157) | G157: =IF(F157>0,"已查到","未查到")
A158: 高中 | B158: 南一 | C158: 化學 | E158: 選修化學I | F158: =COUNTIFS(高中!$A:$A,$B158,高中!$E:$E,$C158,高中!$F:$F,"<>",高中!$C:$C,"",高中!$D:$D,$E158) | G158: =IF(F158>0,"已查到","未查到")
A159: 高中 | B159: 南一 | C159: 化學 | E159: 選修化學II | F159: =COUNTIFS(高中!$A:$A,$B159,高中!$E:$E,$C159,高中!$F:$F,"<>",高中!$C:$C,"",高中!$D:$D,$E159) | G159: =IF(F159>0,"已查到","未查到")
A160: 高中 | B160: 南一 | C160: 化學 | E160: 選修化學III | F160: =COUNTIFS(高中!$A:$A,$B160,高中!$E:$E,$C160,高中!$F:$F,"<>",高中!$C:$C,"",高中!$D:$D,$E160) | G160: =IF(F160>0,"已查到","未查到")
A161: 高中 | B161: 南一 | C161: 化學 | E161: 選修化學IV | F161: =COUNTIFS(高中!$A:$A,$B161,高中!$E:$E,$C161,高中!$F:$F,"<>",高中!$C:$C,"",高中!$D:$D,$E161) | G161: =IF(F161>0,"已查到","未查到")
A162: 國中 | B162: 南一 | C162: 地球科學 | D162: 9 | E162: 上 | F162: =COUNTIFS(國中!$A:$A,$B162,國中!$E:$E,$C162,國中!$F:$F,"<>",國中!$C:$C,$D162,國中!$D:$D,$E162) | G162: =IF(F162>0,"已查到","未查到")
A163: 國中 | B163: 南一 | C163: 地球科學 | D163: 9 | E163: 下 | F163: =COUNTIFS(國中!$A:$A,$B163,國中!$E:$E,$C163,國中!$F:$F,"<>",國中!$C:$C,$D163,國中!$D:$D,$E163) | G163: =IF(F163>0,"已查到","未查到")
A164: 高中 | B164: 南一 | C164: 地球科學 | E164: 基礎地球科學（一） | F164: =COUNTIFS(高中!$A:$A,$B164,高中!$E:$E,$C164,高中!$F:$F,"<>",高中!$C:$C,"",高中!$D:$D,$E164) | G164: =IF(F164>0,"已查到","未查到")
A165: 高中 | B165: 南一 | C165: 地球科學 | E165: 基礎地球科學（二） | F165: =COUNTIFS(高中!$A:$A,$B165,高中!$E:$E,$C165,高中!$F:$F,"<>",高中!$C:$C,"",高中!$D:$D,$E165) | G165: =IF(F165>0,"已查到","未查到")
A166: 高中 | B166: 南一 | C166: 地球科學 | E166: 選修地球科學I | F166: =COUNTIFS(高中!$A:$A,$B166,高中!$E:$E,$C166,高中!$F:$F,"<>",高中!$C:$C,"",高中!$D:$D,$E166) | G166: =IF(F166>0,"已查到","未查到")
A167: 高中 | B167: 南一 | C167: 地球科學 | E167: 選修地球科學II | F167: =COUNTIFS(高中!$A:$A,$B167,高中!$E:$E,$C167,高中!$F:$F,"<>",高中!$C:$C,"",高中!$D:$D,$E167) | G167: =IF(F167>0,"已查到","未查到")
A168: 高中 | B168: 南一 | C168: 地球科學 | E168: 選修地球科學III | F168: =COUNTIFS(高中!$A:$A,$B168,高中!$E:$E,$C168,高中!$F:$F,"<>",高中!$C:$C,"",高中!$D:$D,$E168) | G168: =IF(F168>0,"已查到","未查到")
A169: 高中 | B169: 南一 | C169: 地球科學 | E169: 選修地球科學IV | F169: =COUNTIFS(高中!$A:$A,$B169,高中!$E:$E,$C169,高中!$F:$F,"<>",高中!$C:$C,"",高中!$D:$D,$E169) | G169: =IF(F169>0,"已查到","未查到")
A170: 國中 | B170: 南一 | C170: 歷史 | D170: 7 | E170: 上 | F170: =COUNTIFS(國中!$A:$A,$B170,國中!$E:$E,$C170,國中!$F:$F,"<>",國中!$C:$C,$D170,國中!$D:$D,$E170) | G170: =IF(F170>0,"已查到","未查到")
A171: 國中 | B171: 南一 | C171: 歷史 | D171: 7 | E171: 下 | F171: =COUNTIFS(國中!$A:$A,$B171,國中!$E:$E,$C171,國中!$F:$F,"<>",國中!$C:$C,$D171,國中!$D:$D,$E171) | G171: =IF(F171>0,"已查到","未查到")
A172: 國中 | B172: 南一 | C172: 歷史 | D172: 8 | E172: 上 | F172: =COUNTIFS(國中!$A:$A,$B172,國中!$E:$E,$C172,國中!$F:$F,"<>",國中!$C:$C,$D172,國中!$D:$D,$E172) | G172: =IF(F172>0,"已查到","未查到")
A173: 國中 | B173: 南一 | C173: 歷史 | D173: 8 | E173: 下 | F173: =COUNTIFS(國中!$A:$A,$B173,國中!$E:$E,$C173,國中!$F:$F,"<>",國中!$C:$C,$D173,國中!$D:$D,$E173) | G173: =IF(F173>0,"已查到","未查到")
A174: 國中 | B174: 南一 | C174: 歷史 | D174: 9 | E174: 上 | F174: =COUNTIFS(國中!$A:$A,$B174,國中!$E:$E,$C174,國中!$F:$F,"<>",國中!$C:$C,$D174,國中!$D:$D,$E174) | G174: =IF(F174>0,"已查到","未查到")
A175: 國中 | B175: 南一 | C175: 歷史 | D175: 9 | E175: 下 | F175: =COUNTIFS(國中!$A:$A,$B175,國中!$E:$E,$C175,國中!$F:$F,"<>",國中!$C:$C,$D175,國中!$D:$D,$E175) | G175: =IF(F175>0,"已查到","未查到")
A176: 高中 | B176: 南一 | C176: 歷史 | D176: 10 | E176: 第一冊 | F176: =COUNTIFS(高中!$A:$A,$B176,高中!$E:$E,$C176,高中!$F:$F,"<>",高中!$C:$C,$D176,高中!$D:$D,$E176) | G176: =IF(F176>0,"已查到","未查到")
A177: 高中 | B177: 南一 | C177: 歷史 | D177: 10 | E177: 第二冊 | F177: =COUNTIFS(高中!$A:$A,$B177,高中!$E:$E,$C177,高中!$F:$F,"<>",高中!$C:$C,$D177,高中!$D:$D,$E177) | G177: =IF(F177>0,"已查到","未查到")
A178: 高中 | B178: 南一 | C178: 歷史 | D178: 11 | E178: 第三冊 | F178: =COUNTIFS(高中!$A:$A,$B178,高中!$E:$E,$C178,高中!$F:$F,"<>",高中!$C:$C,$D178,高中!$D:$D,$E178) | G178: =IF(F178>0,"已查到","未查到")
A179: 高中 | B179: 南一 | C179: 歷史 | E179: 加深加廣選修 探究與實作：歷史學探究 | F179: =COUNTIFS(高中!$A:$A,$B179,高中!$E:$E,$C179,高中!$F:$F,"<>",高中!$C:$C,"",高中!$D:$D,$E179) | G179: =IF(F179>0,"已查到","未查到")
A180: 高中 | B180: 南一 | C180: 歷史 | E180: 加深加廣選修 族群、性別與國家的歷史 | F180: =COUNTIFS(高中!$A:$A,$B180,高中!$E:$E,$C180,高中!$F:$F,"<>",高中!$C:$C,"",高中!$D:$D,$E180) | G180: =IF(F180>0,"已查到","未查到")
A181: 高中 | B181: 南一 | C181: 歷史 | E181: 加深加廣選修 科技、環境與藝術的歷史 | F181: =COUNTIFS(高中!$A:$A,$B181,高中!$E:$E,$C181,高中!$F:$F,"<>",高中!$C:$C,"",高中!$D:$D,$E181) | G181: =IF(F181>0,"已查到","未查到")
...
